
{
  "nodes": [
   {"id": "5785",
   "name": "Bernie Cornfeld",
   "type": "http://www.lombardinetworks.net/lombardi.owl#Person"},
  {"id": "5784",
   "name": "Dreyfus",
   "type": "http://www.lombardinetworks.net/lombardi.owl#Person"},
  {"id": "5783",
   "name": "56",
   "type": "http://www.lombardinetworks.net/lombardi.owl#Year"},
  {"id": "5782",
   "name": "60",
   "type": "http://www.lombardinetworks.net/lombardi.owl#Year"},
  {"id": "5781",
   "name": "62",
   "type": "http://www.lombardinetworks.net/lombardi.owl#Year"},
  {"id": "5780",
   "name": "US expatriates",
   "type": "http://www.lombardinetworks.net/lombardi.owl#Person"},
  {"id": "5779",
   "name": "Dreyfus Fund",
   "type": "http://www.lombardinetworks.net/lombardi.owl#Institution"},
  {"id": "5778",
   "name": "Citibank",
   "type": "http://www.lombardinetworks.net/lombardi.owl#Institution"},
  {"id": "5777",
   "name": "Arthur Lipper",
   "type": "http://www.lombardinetworks.net/lombardi.owl#Person"},
  {"id": "5776",
   "name": "US funds",
   "type": "http://www.lombardinetworks.net/lombardi.owl#Institution"},
  {"id": "5775",
   "name": "IIT",
   "type": "http://www.lombardinetworks.net/lombardi.owl#Institution"},
  {"id": "5774",
   "name": "H Buhl",
   "type": "http://www.lombardinetworks.net/lombardi.owl#Person"},
  {"id": "5773",
   "name": "Foreign investors",
   "type": "http://www.lombardinetworks.net/lombardi.owl#Institution"},
  {"id": "5772",
   "name": "Credit Suisse",
   "type": "http://www.lombardinetworks.net/lombardi.owl#Institution"},
  {"id": "5771",
   "name": "FOF",
   "type": "http://www.lombardinetworks.net/lombardi.owl#Institution"},
  {"id": "5770",
   "name": "Lt Gov Ky Wyatt",
   "type": "http://www.lombardinetworks.net/lombardi.owl#Person"},
  {"id": "5769",
   "name": "US mutual funds",
   "type": "http://www.lombardinetworks.net/lombardi.owl#Institution"},
  {"id": "5768",
   "name": "Gov Pat Brown",
   "type": "http://www.lombardinetworks.net/lombardi.owl#Person"},
  {"id": "5767",
   "name": "IIT/2 $ 200 mil",
   "type": "http://www.lombardinetworks.net/lombardi.owl#Institution"},
  {"id": "2486",
   "name": "[1]",
   "type": "http://www.lombardinetworks.net/lombardi.owl#Institution"},
  {"id": "5766",
   "name": "ODB Geneva",
   "type": "http://www.lombardinetworks.net/lombardi.owl#Institution"},
  {"id": "5765",
   "name": "Willkie Farr & Gallagher US atty",
   "type": "http://www.lombardinetworks.net/lombardi.owl#Institution"},
  {"id": "5764",
   "name": "Rosenbaum",
   "type": "http://www.lombardinetworks.net/lombardi.owl#Person"},
  {"id": "5763",
   "name": "ICB",
   "type": "http://www.lombardinetworks.net/lombardi.owl#Institution"},
  {"id": "5762",
   "name": "Ferdman",
   "type": "http://www.lombardinetworks.net/lombardi.owl#Person"},
  {"id": "5761",
   "name": "So American & miscellaneous hot money",
   "type": "http://www.lombardinetworks.net/lombardi.owl#Institution"},
  {"id": "5760",
   "name": "Lansky",
   "type": "http://www.lombardinetworks.net/lombardi.owl#Person"},
  {"id": "2305",
   "name": "[2]",
   "type": "http://www.lombardinetworks.net/lombardi.owl#Institution"},
  {"id": "5759",
   "name": "Lansky apt proj",
   "type": "http://www.lombardinetworks.net/lombardi.owl#Institution"},
  {"id": "5758",
   "name": "65",
   "type": "http://www.lombardinetworks.net/lombardi.owl#Year"},
  {"id": "5757",
   "name": "SEC case",
   "type": "http://www.lombardinetworks.net/lombardi.owl#Institution"},
  {"id": "5756",
   "name": "Seymour Lazar",
   "type": "http://www.lombardinetworks.net/lombardi.owl#Person"},
  {"id": "5755",
   "name": "IOS Panama",
   "type": "http://www.lombardinetworks.net/lombardi.owl#Institution"},
  {"id": "5754",
   "name": "InvCont Services NY",
   "type": "http://www.lombardinetworks.net/lombardi.owl#Institution"},
  {"id": "2319",
   "name": "[3]",
   "type": "http://www.lombardinetworks.net/lombardi.owl#Institution"},
  {"id": "5753",
   "name": "Arthur Andersen",
   "type": "http://www.lombardinetworks.net/lombardi.owl#Person"},
  {"id": "5752",
   "name": "Prince Bernhard",
   "type": "http://www.lombardinetworks.net/lombardi.owl#Person"},
  {"id": "5751",
   "name": "ILI",
   "type": "http://www.lombardinetworks.net/lombardi.owl#Institution"},
  {"id": "5750",
   "name": "John Templeton",
   "type": "http://www.lombardinetworks.net/lombardi.owl#Person"},
  {"id": "5749",
   "name": "j.v. Rothschild Exp",
   "type": "http://www.lombardinetworks.net/lombardi.owl#Institution"},
  {"id": "5748",
   "name": "Rothschild",
   "type": "http://www.lombardinetworks.net/lombardi.owl#Person"},
  {"id": "5747",
   "name": "Alger Fund",
   "type": "http://www.lombardinetworks.net/lombardi.owl#Institution"},
  {"id": "5746",
   "name": "Resorts Int",
   "type": "http://www.lombardinetworks.net/lombardi.owl#Institution"},
  {"id": "5745",
   "name": "Fid Trust",
   "type": "http://www.lombardinetworks.net/lombardi.owl#Institution"},
  {"id": "5744",
   "name": "Clapp",
   "type": "http://www.lombardinetworks.net/lombardi.owl#Person"},
  {"id": "5743",
   "name": "Cowatt",
   "type": "http://www.lombardinetworks.net/lombardi.owl#Person"},
  {"id": "5742",
   "name": "Sayad",
   "type": "http://www.lombardinetworks.net/lombardi.owl#Person"},
  {"id": "5741",
   "name": "Joel Martin",
   "type": "http://www.lombardinetworks.net/lombardi.owl#Person"},
  {"id": "5740",
   "name": "67",
   "type": "http://www.lombardinetworks.net/lombardi.owl#Year"},
  {"id": "5739",
   "name": "IIT/3 $ 474 mil",
   "type": "http://www.lombardinetworks.net/lombardi.owl#Institution"},
  {"id": "5738",
   "name": "Eon Corp",
   "type": "http://www.lombardinetworks.net/lombardi.owl#Institution"},
  {"id": "5737",
   "name": "settle w/ SEC",
   "type": "http://www.lombardinetworks.net/lombardi.owl#Institution"},
  {"id": "5736",
   "name": "68",
   "type": "http://www.lombardinetworks.net/lombardi.owl#Year"},
  {"id": "5735",
   "name": "Sir Eric",
   "type": "http://www.lombardinetworks.net/lombardi.owl#Person"},
  {"id": "5734",
   "name": "C&L",
   "type": "http://www.lombardinetworks.net/lombardi.owl#Institution"},
  {"id": "5733",
   "name": "James Roosevelt",
   "type": "http://www.lombardinetworks.net/lombardi.owl#Person"},
  {"id": "5732",
   "name": "IPI $ 50 mill re cash",
   "type": "http://www.lombardinetworks.net/lombardi.owl#Institution"},
  {"id": "5731",
   "name": "IIT/4",
   "type": "http://www.lombardinetworks.net/lombardi.owl#Institution"},
  {"id": "5730",
   "name": "ICC",
   "type": "http://www.lombardinetworks.net/lombardi.owl#Institution"},
  {"id": "5729",
   "name": "Vesco",
   "type": "http://www.lombardinetworks.net/lombardi.owl#Institution"},
  {"id": "5728",
   "name": "BofA",
   "type": "http://www.lombardinetworks.net/lombardi.owl#Institution"},
  {"id": "5727",
   "name": "Prudential",
   "type": "http://www.lombardinetworks.net/lombardi.owl#Institution"},
  {"id": "5726",
   "name": "CUC",
   "type": "http://www.lombardinetworks.net/lombardi.owl#Institution"},
  {"id": "5725",
   "name": "VCL Intl re",
   "type": "http://www.lombardinetworks.net/lombardi.owl#Institution"},
  {"id": "5724",
   "name": "69",
   "type": "http://www.lombardinetworks.net/lombardi.owl#Year"},
  {"id": "5723",
   "name": "Canada Fund",
   "type": "http://www.lombardinetworks.net/lombardi.owl#Institution"},
  {"id": "5722",
   "name": "Gulf & Western",
   "type": "http://www.lombardinetworks.net/lombardi.owl#Institution"},
  {"id": "5721",
   "name": "John M King",
   "type": "http://www.lombardinetworks.net/lombardi.owl#Person"},
  {"id": "5720",
   "name": "FOF/2",
   "type": "http://www.lombardinetworks.net/lombardi.owl#Institution"},
  {"id": "5719",
   "name": "King Resources",
   "type": "http://www.lombardinetworks.net/lombardi.owl#Institution"},
  {"id": "5718",
   "name": "Nixon",
   "type": "http://www.lombardinetworks.net/lombardi.owl#Person"},
  {"id": "5717",
   "name": "Stans",
   "type": "http://www.lombardinetworks.net/lombardi.owl#Person"},
  {"id": "5716",
   "name": "Sinai oil",
   "type": "http://www.lombardinetworks.net/lombardi.owl#Institution"},
  {"id": "5715",
   "name": "Mitchell",
   "type": "http://www.lombardinetworks.net/lombardi.owl#Person"},
  {"id": "5714",
   "name": "Global Nat Reso",
   "type": "http://www.lombardinetworks.net/lombardi.owl#Institution"},
  {"id": "5713",
   "name": "70",
   "type": "http://www.lombardinetworks.net/lombardi.owl#Year"},
  {"id": "5712",
   "name": "$ 2 bil assets",
   "type": "http://www.lombardinetworks.net/lombardi.owl#Institution"},
  {"id": "5711",
   "name": "IOS Brazil",
   "type": "http://www.lombardinetworks.net/lombardi.owl#Institution"},
  {"id": "2473",
   "name": "[4]",
   "type": "http://www.lombardinetworks.net/lombardi.owl#Institution"},
  {"id": "5710",
   "name": "Rapid American",
   "type": "http://www.lombardinetworks.net/lombardi.owl#Institution"},
  {"id": "5709",
   "name": "M. Riklis",
   "type": "http://www.lombardinetworks.net/lombardi.owl#Person"},
  {"id": "2472",
   "name": "[5]",
   "type": "http://www.lombardinetworks.net/lombardi.owl#Institution"},
  {"id": "2470",
   "name": "[6]",
   "type": "http://www.lombardinetworks.net/lombardi.owl#Institution"},
  {"id": "2467",
   "name": "[7]",
   "type": "http://www.lombardinetworks.net/lombardi.owl#Institution"},
  {"id": "3556",
   "name": "[8]",
   "type": "http://www.lombardinetworks.net/lombardi.owl#Person"},
  {"id": "3553",
   "name": "[9]",
   "type": "http://www.lombardinetworks.net/lombardi.owl#Institution"},
  {"id": "3552",
   "name": "[10]",
   "type": "http://www.lombardinetworks.net/lombardi.owl#Person"},
  {"id": "3550",
   "name": "[11]",
   "type": "http://www.lombardinetworks.net/lombardi.owl#Institution"},
  {"id": "3549",
   "name": "[12]",
   "type": "http://www.lombardinetworks.net/lombardi.owl#Person"},
  {"id": "3548",
   "name": "[13]",
   "type": "http://www.lombardinetworks.net/lombardi.owl#Person"},
  {"id": "5708",
   "name": "[14]",
   "type": "http://www.lombardinetworks.net/lombardi.owl#Institution"},
  {"id": "5707",
   "name": "[15]",
   "type": "http://www.lombardinetworks.net/lombardi.owl#Institution"},
  {"id": "5706",
   "name": "[16]",
   "type": "http://www.lombardinetworks.net/lombardi.owl#Institution"},
  {"id": "5705",
   "name": "10k acres Palm Springs",
   "type": "http://www.lombardinetworks.net/lombardi.owl#Institution"}

   ],
   "links": [
   {"source": "5785",
   "target": "5784",
   "amount": "",
   "type": "http://www.lombardinetworks.net/lombardi.owl#Connection"},
  {"source": "5784",
   "target": "5783",
   "amount": "",
   "type": "http://www.lombardinetworks.net/lombardi.owl#Connection"},
  {"source": "5784",
   "target": "2470",
   "amount": "",
   "type": "http://www.lombardinetworks.net/lombardi.owl#InfluenceControl"},
  {"source": "5783",
   "target": "5782",
   "amount": "",
   "type": "http://www.lombardinetworks.net/lombardi.owl#YearArrow"},
  {"source": "5783",
   "target": "5779",
   "amount": "",
   "type": "http://www.lombardinetworks.net/lombardi.owl#FinancialTransaction"},
  {"source": "5783",
   "target": "5778",
   "amount": "",
   "type": "http://www.lombardinetworks.net/lombardi.owl#FinancialTransaction"},
  {"source": "5782",
   "target": "5781",
   "amount": "",
   "type": "http://www.lombardinetworks.net/lombardi.owl#YearArrow"},
  {"source": "5782",
   "target": "5775",
   "amount": "",
   "type": "http://www.lombardinetworks.net/lombardi.owl#Connection"},
  {"source": "5782",
   "target": "5774",
   "amount": "",
   "type": "http://www.lombardinetworks.net/lombardi.owl#Connection"},
  {"source": "5781",
   "target": "5772",
   "amount": "",
   "type": "http://www.lombardinetworks.net/lombardi.owl#FinancialConnection"},
  {"source": "5781",
   "target": "5771",
   "amount": "",
   "type": "http://www.lombardinetworks.net/lombardi.owl#Connection"},
  {"source": "5781",
   "target": "5767",
   "amount": "",
   "type": "http://www.lombardinetworks.net/lombardi.owl#Connection"},
  {"source": "5781",
   "target": "2486",
   "amount": "",
   "type": "http://www.lombardinetworks.net/lombardi.owl#YearArrow"},
  {"source": "5780",
   "target": "5783",
   "amount": "",
   "type": "http://www.lombardinetworks.net/lombardi.owl#FinancialTransaction"},
  {"source": "5780",
   "target": "5782",
   "amount": "",
   "type": "http://www.lombardinetworks.net/lombardi.owl#FinancialTransaction"},
  {"source": "5778",
   "target": "5777",
   "amount": "",
   "type": "http://www.lombardinetworks.net/lombardi.owl#FinancialTransaction"},
  {"source": "5777",
   "target": "5776",
   "amount": "",
   "type": "http://www.lombardinetworks.net/lombardi.owl#FinancialTransaction"},
  {"source": "5775",
   "target": "5774",
   "amount": "",
   "type": "http://www.lombardinetworks.net/lombardi.owl#Connection"},
  {"source": "5773",
   "target": "5781",
   "amount": "",
   "type": "http://www.lombardinetworks.net/lombardi.owl#FinancialTransaction"},
  {"source": "5772",
   "target": "5777",
   "amount": "",
   "type": "http://www.lombardinetworks.net/lombardi.owl#FinancialTransaction"},
  {"source": "5771",
   "target": "5770",
   "amount": "",
   "type": "http://www.lombardinetworks.net/lombardi.owl#Connection"},
  {"source": "5771",
   "target": "5769",
   "amount": "",
   "type": "http://www.lombardinetworks.net/lombardi.owl#FinancialTransaction"},
  {"source": "5771",
   "target": "5768",
   "amount": "",
   "type": "http://www.lombardinetworks.net/lombardi.owl#Connection"},
  {"source": "2486",
   "target": "5766",
   "amount": "",
   "type": "http://www.lombardinetworks.net/lombardi.owl#Connection"},
  {"source": "2486",
   "target": "5765",
   "amount": "",
   "type": "http://www.lombardinetworks.net/lombardi.owl#Connection"},
  {"source": "2486",
   "target": "5764",
   "amount": "",
   "type": "http://www.lombardinetworks.net/lombardi.owl#Connection"},
  {"source": "2486",
   "target": "2305",
   "amount": "",
   "type": "http://www.lombardinetworks.net/lombardi.owl#Connection"},
  {"source": "2486",
   "target": "5759",
   "amount": "",
   "type": "http://www.lombardinetworks.net/lombardi.owl#FinancialConnection"},
  {"source": "2486",
   "target": "5758",
   "amount": "",
   "type": "http://www.lombardinetworks.net/lombardi.owl#YearArrow"},
  {"source": "5764",
   "target": "5763",
   "amount": "",
   "type": "http://www.lombardinetworks.net/lombardi.owl#Connection"},
  {"source": "5763",
   "target": "2486",
   "amount": "",
   "type": "http://www.lombardinetworks.net/lombardi.owl#FinancialTransaction"},
  {"source": "5763",
   "target": "2305",
   "amount": "",
   "type": "http://www.lombardinetworks.net/lombardi.owl#Connection"},
  {"source": "5762",
   "target": "5763",
   "amount": "",
   "type": "http://www.lombardinetworks.net/lombardi.owl#Connection"},
  {"source": "5761",
   "target": "5763",
   "amount": "",
   "type": "http://www.lombardinetworks.net/lombardi.owl#FinancialTransaction"},
  {"source": "5760",
   "target": "5763",
   "amount": "",
   "type": "http://www.lombardinetworks.net/lombardi.owl#Connection"},
  {"source": "5758",
   "target": "2319",
   "amount": "",
   "type": "http://www.lombardinetworks.net/lombardi.owl#YearArrow"},
  {"source": "5757",
   "target": "5758",
   "amount": "",
   "type": "http://www.lombardinetworks.net/lombardi.owl#Association"},
  {"source": "5756",
   "target": "5758",
   "amount": "",
   "type": "http://www.lombardinetworks.net/lombardi.owl#FinancialTransaction"},
  {"source": "5755",
   "target": "5758",
   "amount": "",
   "type": "http://www.lombardinetworks.net/lombardi.owl#InfluenceControl"},
  {"source": "5754",
   "target": "5758",
   "amount": "",
   "type": "http://www.lombardinetworks.net/lombardi.owl#Connection"},
  {"source": "2319",
   "target": "5751",
   "amount": "",
   "type": "http://www.lombardinetworks.net/lombardi.owl#Connection"},
  {"source": "2319",
   "target": "5749",
   "amount": "",
   "type": "http://www.lombardinetworks.net/lombardi.owl#InfluenceControl"},
  {"source": "2319",
   "target": "5747",
   "amount": "",
   "type": "http://www.lombardinetworks.net/lombardi.owl#Connection"},
  {"source": "2319",
   "target": "5740",
   "amount": "",
   "type": "http://www.lombardinetworks.net/lombardi.owl#YearArrow"},
  {"source": "5753",
   "target": "2319",
   "amount": "",
   "type": "http://www.lombardinetworks.net/lombardi.owl#Connection"},
  {"source": "5752",
   "target": "2319",
   "amount": "",
   "type": "http://www.lombardinetworks.net/lombardi.owl#Connection"},
  {"source": "5750",
   "target": "5751",
   "amount": "",
   "type": "http://www.lombardinetworks.net/lombardi.owl#FinancialTransaction"},
  {"source": "5748",
   "target": "5749",
   "amount": "",
   "type": "http://www.lombardinetworks.net/lombardi.owl#InfluenceControl"},
  {"source": "5747",
   "target": "5746",
   "amount": "",
   "type": "http://www.lombardinetworks.net/lombardi.owl#FinancialTransaction"},
  {"source": "5745",
   "target": "5746",
   "amount": "",
   "type": "http://www.lombardinetworks.net/lombardi.owl#FinancialTransaction"},
  {"source": "5745",
   "target": "5744",
   "amount": "",
   "type": "http://www.lombardinetworks.net/lombardi.owl#Connection"},
  {"source": "5745",
   "target": "5743",
   "amount": "",
   "type": "http://www.lombardinetworks.net/lombardi.owl#Connection"},
  {"source": "5745",
   "target": "5742",
   "amount": "",
   "type": "http://www.lombardinetworks.net/lombardi.owl#Connection"},
  {"source": "5741",
   "target": "5746",
   "amount": "",
   "type": "http://www.lombardinetworks.net/lombardi.owl#Connection"},
  {"source": "5740",
   "target": "5738",
   "amount": "",
   "type": "http://www.lombardinetworks.net/lombardi.owl#FinancialTransaction"},
  {"source": "5740",
   "target": "5736",
   "amount": "",
   "type": "http://www.lombardinetworks.net/lombardi.owl#YearArrow"},
  {"source": "5739",
   "target": "5740",
   "amount": "",
   "type": "http://www.lombardinetworks.net/lombardi.owl#Connection"},
  {"source": "5737",
   "target": "5740",
   "amount": "",
   "type": "http://www.lombardinetworks.net/lombardi.owl#Association"},
  {"source": "5736",
   "target": "5732",
   "amount": "",
   "type": "http://www.lombardinetworks.net/lombardi.owl#Connection"},
  {"source": "5736",
   "target": "5731",
   "amount": "",
   "type": "http://www.lombardinetworks.net/lombardi.owl#Connection"},
  {"source": "5736",
   "target": "5725",
   "amount": "",
   "type": "http://www.lombardinetworks.net/lombardi.owl#Connection"},
  {"source": "5736",
   "target": "5724",
   "amount": "",
   "type": "http://www.lombardinetworks.net/lombardi.owl#YearArrow"},
  {"source": "5735",
   "target": "5736",
   "amount": "",
   "type": "http://www.lombardinetworks.net/lombardi.owl#InfluenceControl"},
  {"source": "5734",
   "target": "5736",
   "amount": "",
   "type": "http://www.lombardinetworks.net/lombardi.owl#Connection"},
  {"source": "5733",
   "target": "5736",
   "amount": "",
   "type": "http://www.lombardinetworks.net/lombardi.owl#InfluenceControl"},
  {"source": "5731",
   "target": "5730",
   "amount": "",
   "type": "http://www.lombardinetworks.net/lombardi.owl#FinancialTransaction"},
  {"source": "5730",
   "target": "5725",
   "amount": "",
   "type": "http://www.lombardinetworks.net/lombardi.owl#InfluenceControl"},
  {"source": "5729",
   "target": "5730",
   "amount": "",
   "type": "http://www.lombardinetworks.net/lombardi.owl#InfluenceControl"},
  {"source": "5729",
   "target": "5726",
   "amount": "",
   "type": "http://www.lombardinetworks.net/lombardi.owl#FinancialTransaction"},
  {"source": "5728",
   "target": "5729",
   "amount": "",
   "type": "http://www.lombardinetworks.net/lombardi.owl#FinancialTransaction"},
  {"source": "5727",
   "target": "5729",
   "amount": "",
   "type": "http://www.lombardinetworks.net/lombardi.owl#FinancialTransaction"},
  {"source": "5724",
   "target": "5726",
   "amount": "",
   "type": "http://www.lombardinetworks.net/lombardi.owl#FinancialTransaction"},
  {"source": "5724",
   "target": "5720",
   "amount": "",
   "type": "http://www.lombardinetworks.net/lombardi.owl#Connection"},
  {"source": "5724",
   "target": "5714",
   "amount": "",
   "type": "http://www.lombardinetworks.net/lombardi.owl#Connection"},
  {"source": "5724",
   "target": "5713",
   "amount": "",
   "type": "http://www.lombardinetworks.net/lombardi.owl#YearArrow"},
  {"source": "5723",
   "target": "5724",
   "amount": "",
   "type": "http://www.lombardinetworks.net/lombardi.owl#InfluenceControl"},
  {"source": "5722",
   "target": "5726",
   "amount": "",
   "type": "http://www.lombardinetworks.net/lombardi.owl#FinancialTransaction"},
  {"source": "5721",
   "target": "5726",
   "amount": "",
   "type": "http://www.lombardinetworks.net/lombardi.owl#FinancialTransaction"},
  {"source": "5721",
   "target": "5719",
   "amount": "",
   "type": "http://www.lombardinetworks.net/lombardi.owl#InfluenceControl"},
  {"source": "5721",
   "target": "5720",
   "amount": "",
   "type": "http://www.lombardinetworks.net/lombardi.owl#FinancialTransaction"},
  {"source": "5721",
   "target": "5718",
   "amount": "",
   "type": "http://www.lombardinetworks.net/lombardi.owl#Connection"},
  {"source": "5721",
   "target": "5717",
   "amount": "",
   "type": "http://www.lombardinetworks.net/lombardi.owl#Connection"},
  {"source": "5721",
   "target": "5716",
   "amount": "",
   "type": "http://www.lombardinetworks.net/lombardi.owl#Connection"},
  {"source": "5721",
   "target": "5715",
   "amount": "",
   "type": "http://www.lombardinetworks.net/lombardi.owl#Connection"},
  {"source": "5720",
   "target": "5719",
   "amount": "",
   "type": "http://www.lombardinetworks.net/lombardi.owl#FinancialTransaction"},
  {"source": "5713",
   "target": "5712",
   "amount": "",
   "type": "http://www.lombardinetworks.net/lombardi.owl#Connection"},
  {"source": "5713",
   "target": "5711",
   "amount": "",
   "type": "http://www.lombardinetworks.net/lombardi.owl#Connection"},
  {"source": "5713",
   "target": "5710",
   "amount": "",
   "type": "http://www.lombardinetworks.net/lombardi.owl#Connection"},
  {"source": "5713",
   "target": "2472",
   "amount": "",
   "type": "http://www.lombardinetworks.net/lombardi.owl#YearArrow"},
  {"source": "5711",
   "target": "2473",
   "amount": "",
   "type": "http://www.lombardinetworks.net/lombardi.owl#SaleProperty"},
  {"source": "5710",
   "target": "5709",
   "amount": "",
   "type": "http://www.lombardinetworks.net/lombardi.owl#InfluenceControl"},
  {"source": "5709",
   "target": "5713",
   "amount": "",
   "type": "http://www.lombardinetworks.net/lombardi.owl#FinancialTransaction"},
  {"source": "2470",
   "target": "2467",
   "amount": "",
   "type": "http://www.lombardinetworks.net/lombardi.owl#YearArrow"},
  {"source": "2467",
   "target": "3556",
   "amount": "",
   "type": "http://www.lombardinetworks.net/lombardi.owl#YearArrow"},
  {"source": "3556",
   "target": "3553",
   "amount": "",
   "type": "http://www.lombardinetworks.net/lombardi.owl#YearArrow"},
  {"source": "3553",
   "target": "3552",
   "amount": "",
   "type": "http://www.lombardinetworks.net/lombardi.owl#YearArrow"},
  {"source": "3552",
   "target": "3550",
   "amount": "",
   "type": "http://www.lombardinetworks.net/lombardi.owl#YearArrow"},
  {"source": "3550",
   "target": "3549",
   "amount": "",
   "type": "http://www.lombardinetworks.net/lombardi.owl#YearArrow"},
  {"source": "3549",
   "target": "3548",
   "amount": "",
   "type": "http://www.lombardinetworks.net/lombardi.owl#YearArrow"},
  {"source": "3549",
   "target": "5738",
   "amount": "",
   "type": "http://www.lombardinetworks.net/lombardi.owl#FinancialTransaction"},
  {"source": "3548",
   "target": "5708",
   "amount": "",
   "type": "http://www.lombardinetworks.net/lombardi.owl#YearArrow"},
  {"source": "5708",
   "target": "5707",
   "amount": "",
   "type": "http://www.lombardinetworks.net/lombardi.owl#YearArrow"},
  {"source": "5707",
   "target": "5706",
   "amount": "",
   "type": "http://www.lombardinetworks.net/lombardi.owl#YearArrow"},
  {"source": "5707",
   "target": "5705",
   "amount": "",
   "type": "http://www.lombardinetworks.net/lombardi.owl#FinancialTransaction"}
 ]
}