
{
  "nodes": [
   {"id": "1080",
   "name": "NW",
   "type": "http://www.lombardinetworks.net/lombardi.owl#Institution"},
  {"id": "1079",
   "name": "Irvani",
   "type": "http://www.lombardinetworks.net/lombardi.owl#Person"},
  {"id": "1078",
   "name": "Richard Helms",
   "type": "http://www.lombardinetworks.net/lombardi.owl#Person"},
  {"id": "1077",
   "name": "Safeer",
   "type": "http://www.lombardinetworks.net/lombardi.owl#Institution"},
  {"id": "1076",
   "name": "BFA",
   "type": "http://www.lombardinetworks.net/lombardi.owl#Institution"},
  {"id": "941",
   "name": "Roy Carlson",
   "type": "http://www.lombardinetworks.net/lombardi.owl#Person"},
  {"id": "1075",
   "name": "Gheiki Hunaar",
   "type": "http://www.lombardinetworks.net/lombardi.owl#Person"},
  {"id": "925",
   "name": "Burt Lance",
   "type": "http://www.lombardinetworks.net/lombardi.owl#Person"},
  {"id": "1074",
   "name": "NBG",
   "type": "http://www.lombardinetworks.net/lombardi.owl#Institution"},
  {"id": "922",
   "name": "Robert Altman",
   "type": "http://www.lombardinetworks.net/lombardi.owl#Person"},
  {"id": "1073",
   "name": "Clark Clifford",
   "type": "http://www.lombardinetworks.net/lombardi.owl#Person"},
  {"id": "1072",
   "name": "Gen Olmsted",
   "type": "http://www.lombardinetworks.net/lombardi.owl#Person"},
  {"id": "1071",
   "name": "Int'l Bk",
   "type": "http://www.lombardinetworks.net/lombardi.owl#Institution"},
  {"id": "1070",
   "name": "Fin gen 1st Amer",
   "type": "http://www.lombardinetworks.net/lombardi.owl#Institution"},
  {"id": "1069",
   "name": "ICIC",
   "type": "http://www.lombardinetworks.net/lombardi.owl#Institution"},
  {"id": "1068",
   "name": "Melli Group",
   "type": "http://www.lombardinetworks.net/lombardi.owl#Institution"},
  {"id": "1067",
   "name": "Iran Arab Bk",
   "type": "http://www.lombardinetworks.net/lombardi.owl#Institution"},
  {"id": "1066",
   "name": "BCCI",
   "type": "http://www.lombardinetworks.net/lombardi.owl#Institution"},
  {"id": "1065",
   "name": "Ajman Arab",
   "type": "http://www.lombardinetworks.net/lombardi.owl#Person"},
  {"id": "1064",
   "name": "Guillermo Hc",
   "type": "http://www.lombardinetworks.net/lombardi.owl#Person"},
  {"id": "1063",
   "name": "Walter S Surrey",
   "type": "http://www.lombardinetworks.net/lombardi.owl#Person"},
  {"id": "1062",
   "name": "ESM Securities",
   "type": "http://www.lombardinetworks.net/lombardi.owl#Institution"},
  {"id": "1061",
   "name": "World Finan.",
   "type": "http://www.lombardinetworks.net/lombardi.owl#Institution"},
  {"id": "1060",
   "name": "1st Ky",
   "type": "http://www.lombardinetworks.net/lombardi.owl#Institution"},
  {"id": "897",
   "name": "Randall Attkisson",
   "type": "http://www.lombardinetworks.net/lombardi.owl#Person"},
  {"id": "1059",
   "name": "William Colby",
   "type": "http://www.lombardinetworks.net/lombardi.owl#Person"},
  {"id": "903",
   "name": "Donald Beazley",
   "type": "http://www.lombardinetworks.net/lombardi.owl#Person"},
  {"id": "1058",
   "name": "Moscow Narodny Bk",
   "type": "http://www.lombardinetworks.net/lombardi.owl#Institution"},
  {"id": "914",
   "name": "Price Waterhouse",
   "type": "http://www.lombardinetworks.net/lombardi.owl#Institution"},
  {"id": "911",
   "name": "Bruce Campbell",
   "type": "http://www.lombardinetworks.net/lombardi.owl#Person"},
  {"id": "893",
   "name": "London Cap Securities",
   "type": "http://www.lombardinetworks.net/lombardi.owl#Institution"},
  {"id": "892",
   "name": "John Stonehouse",
   "type": "http://www.lombardinetworks.net/lombardi.owl#Person"},
  {"id": "1057",
   "name": "Homestead (Fl) Bank",
   "type": "http://www.lombardinetworks.net/lombardi.owl#Institution"},
  {"id": "1056",
   "name": "Paul Helliwell",
   "type": "http://www.lombardinetworks.net/lombardi.owl#Person"},
  {"id": "1055",
   "name": "Castle",
   "type": "http://www.lombardinetworks.net/lombardi.owl#Institution"},
  {"id": "1054",
   "name": "Nugan Hand",
   "type": "http://www.lombardinetworks.net/lombardi.owl#Person"},
  {"id": "1053",
   "name": "Mike Hand",
   "type": "http://www.lombardinetworks.net/lombardi.owl#Person"},
  {"id": "1052",
   "name": " ",
   "type": "http://www.lombardinetworks.net/lombardi.owl#Institution"},
  {"id": "1051",
   "name": "Merc",
   "type": "http://www.lombardinetworks.net/lombardi.owl#Institution"},
  {"id": "884",
   "name": "Daniel K. Ludwig",
   "type": "http://www.lombardinetworks.net/lombardi.owl#Person"}

   ],
   "links": [
   {"source": "1080",
   "target": "1068",
   "amount": "",
   "type": "http://www.lombardinetworks.net/lombardi.owl#InfluenceControl"},
  {"source": "1080",
   "target": "1077",
   "amount": "",
   "type": "http://www.lombardinetworks.net/lombardi.owl#InfluenceControl"},
  {"source": "1079",
   "target": "1068",
   "amount": "",
   "type": "http://www.lombardinetworks.net/lombardi.owl#InfluenceControl"},
  {"source": "1079",
   "target": "1080",
   "amount": "",
   "type": "http://www.lombardinetworks.net/lombardi.owl#InfluenceControl"},
  {"source": "1079",
   "target": "1077",
   "amount": "",
   "type": "http://www.lombardinetworks.net/lombardi.owl#InfluenceControl"},
  {"source": "1078",
   "target": "1077",
   "amount": "",
   "type": "http://www.lombardinetworks.net/lombardi.owl#InfluenceControl"},
  {"source": "1076",
   "target": "1066",
   "amount": "",
   "type": "http://www.lombardinetworks.net/lombardi.owl#InfluenceControl"},
  {"source": "941",
   "target": "1077",
   "amount": "",
   "type": "http://www.lombardinetworks.net/lombardi.owl#InfluenceControl"},
  {"source": "941",
   "target": "1076",
   "amount": "",
   "type": "http://www.lombardinetworks.net/lombardi.owl#InfluenceControl"},
  {"source": "941",
   "target": "1074",
   "amount": "",
   "type": "http://www.lombardinetworks.net/lombardi.owl#InfluenceControl"},
  {"source": "1075",
   "target": "1074",
   "amount": "",
   "type": "http://www.lombardinetworks.net/lombardi.owl#InfluenceControl"},
  {"source": "925",
   "target": "1074",
   "amount": "",
   "type": "http://www.lombardinetworks.net/lombardi.owl#InfluenceControl"},
  {"source": "922",
   "target": "1070",
   "amount": "",
   "type": "http://www.lombardinetworks.net/lombardi.owl#InfluenceControl"},
  {"source": "1073",
   "target": "1070",
   "amount": "",
   "type": "http://www.lombardinetworks.net/lombardi.owl#InfluenceControl"},
  {"source": "1072",
   "target": "1071",
   "amount": "",
   "type": "http://www.lombardinetworks.net/lombardi.owl#InfluenceControl"},
  {"source": "1071",
   "target": "1070",
   "amount": "",
   "type": "http://www.lombardinetworks.net/lombardi.owl#InfluenceControl"},
  {"source": "1071",
   "target": "1051",
   "amount": "",
   "type": "http://www.lombardinetworks.net/lombardi.owl#InfluenceControl"},
  {"source": "1070",
   "target": "1074",
   "amount": "",
   "type": "http://www.lombardinetworks.net/lombardi.owl#Association"},
  {"source": "1069",
   "target": "1070",
   "amount": "",
   "type": "http://www.lombardinetworks.net/lombardi.owl#InfluenceControl"},
  {"source": "1069",
   "target": "914",
   "amount": "",
   "type": "http://www.lombardinetworks.net/lombardi.owl#Association"},
  {"source": "1067",
   "target": "1068",
   "amount": "",
   "type": "http://www.lombardinetworks.net/lombardi.owl#Association"},
  {"source": "1066",
   "target": "1069",
   "amount": "",
   "type": "http://www.lombardinetworks.net/lombardi.owl#InfluenceControl"},
  {"source": "1066",
   "target": "1065",
   "amount": "",
   "type": "http://www.lombardinetworks.net/lombardi.owl#InfluenceControl"},
  {"source": "1066",
   "target": "1067",
   "amount": "",
   "type": "http://www.lombardinetworks.net/lombardi.owl#InfluenceControl"},
  {"source": "1065",
   "target": "1069",
   "amount": "",
   "type": "http://www.lombardinetworks.net/lombardi.owl#Association"},
  {"source": "1065",
   "target": "1061",
   "amount": "",
   "type": "http://www.lombardinetworks.net/lombardi.owl#InfluenceControl"},
  {"source": "1064",
   "target": "1061",
   "amount": "",
   "type": "http://www.lombardinetworks.net/lombardi.owl#InfluenceControl"},
  {"source": "1063",
   "target": "1061",
   "amount": "",
   "type": "http://www.lombardinetworks.net/lombardi.owl#InfluenceControl"},
  {"source": "1062",
   "target": "1061",
   "amount": "",
   "type": "http://www.lombardinetworks.net/lombardi.owl#Association"},
  {"source": "1062",
   "target": "903",
   "amount": "",
   "type": "http://www.lombardinetworks.net/lombardi.owl#Association"},
  {"source": "1060",
   "target": "1061",
   "amount": "",
   "type": "http://www.lombardinetworks.net/lombardi.owl#InfluenceControl"},
  {"source": "897",
   "target": "1060",
   "amount": "",
   "type": "http://www.lombardinetworks.net/lombardi.owl#InfluenceControl"},
  {"source": "897",
   "target": "1054",
   "amount": "",
   "type": "http://www.lombardinetworks.net/lombardi.owl#InfluenceControl"},
  {"source": "1059",
   "target": "1054",
   "amount": "",
   "type": "http://www.lombardinetworks.net/lombardi.owl#Association"},
  {"source": "903",
   "target": "893",
   "amount": "",
   "type": "http://www.lombardinetworks.net/lombardi.owl#InfluenceControl"},
  {"source": "903",
   "target": "1054",
   "amount": "",
   "type": "http://www.lombardinetworks.net/lombardi.owl#InfluenceControl"},
  {"source": "1058",
   "target": "1061",
   "amount": "",
   "type": "http://www.lombardinetworks.net/lombardi.owl#Association"},
  {"source": "911",
   "target": "1069",
   "amount": "",
   "type": "http://www.lombardinetworks.net/lombardi.owl#InfluenceControl"},
  {"source": "911",
   "target": "1054",
   "amount": "",
   "type": "http://www.lombardinetworks.net/lombardi.owl#InfluenceControl"},
  {"source": "892",
   "target": "893",
   "amount": "",
   "type": "http://www.lombardinetworks.net/lombardi.owl#InfluenceControl"},
  {"source": "1056",
   "target": "1055",
   "amount": "",
   "type": "http://www.lombardinetworks.net/lombardi.owl#InfluenceControl"},
  {"source": "1055",
   "target": "1057",
   "amount": "",
   "type": "http://www.lombardinetworks.net/lombardi.owl#InfluenceControl"},
  {"source": "1054",
   "target": "1057",
   "amount": "",
   "type": "http://www.lombardinetworks.net/lombardi.owl#BlockedFailed"},
  {"source": "1054",
   "target": "893",
   "amount": "",
   "type": "http://www.lombardinetworks.net/lombardi.owl#BlockedFailed"},
  {"source": "1054",
   "target": "1058",
   "amount": "",
   "type": "http://www.lombardinetworks.net/lombardi.owl#Association"},
  {"source": "1054",
   "target": "914",
   "amount": "",
   "type": "http://www.lombardinetworks.net/lombardi.owl#Association"},
  {"source": "1053",
   "target": "1054",
   "amount": "",
   "type": "http://www.lombardinetworks.net/lombardi.owl#InfluenceControl"},
  {"source": "1053",
   "target": "1052",
   "amount": "",
   "type": "http://www.lombardinetworks.net/lombardi.owl#InfluenceControl"},
  {"source": "1051",
   "target": "914",
   "amount": "",
   "type": "http://www.lombardinetworks.net/lombardi.owl#Association"},
  {"source": "1051",
   "target": "911",
   "amount": "",
   "type": "http://www.lombardinetworks.net/lombardi.owl#Association"},
  {"source": "1051",
   "target": "1055",
   "amount": "",
   "type": "http://www.lombardinetworks.net/lombardi.owl#InfluenceControl"},
  {"source": "884",
   "target": "1052",
   "amount": "",
   "type": "http://www.lombardinetworks.net/lombardi.owl#InfluenceControl"},
  {"source": "884",
   "target": "1051",
   "amount": "",
   "type": "http://www.lombardinetworks.net/lombardi.owl#InfluenceControl"}
 ]
}