{"nodes":[{"id":"vendor-0","label":"vendor-0","color":"#00bcd4","type":"square","size":5.502499999999998,"metadata":{"category":"vendor","transactions":[{"delivery_time":"4 days","note":"1","date":"2016-06-15T18:29:00+02:00","text":"---","prod_id":"/listing/1873/"},{"delivery_time":"3 days","note":"1","date":"2016-06-13T00:31:00+02:00","text":"Fast, discreet, product as described. Great vendor.","prod_id":"/listing/1873/"},{"delivery_time":"Not specified","note":"1","date":"2016-05-16T07:27:00+02:00","text":"Great product. Thanks!","prod_id":"/listing/1873/"},{"delivery_time":"3 days","note":"1","date":"2016-05-05T21:29:00+02:00","text":"Very good quality and stealth!","prod_id":"/listing/1873/"},{"delivery_time":"10 days","note":"1","date":"2016-05-03T03:50:00+02:00","text":"Communication: N/A. Speed: 4/5. Stealth: 4/5. Product: 5/5.","prod_id":"/listing/1873/"},{"delivery_time":"4 days","note":"1","date":"2016-04-22T20:23:00+02:00","text":"---","prod_id":"/listing/1873/"},{"delivery_time":"5 days","note":"1","date":"2016-04-18T00:54:00+02:00","text":"---","prod_id":"/listing/1873/"},{"delivery_time":"7 days","note":"1","date":"2016-04-12T00:59:00+02:00","text":"---","prod_id":"/listing/1873/"},{"delivery_time":"3 days","note":"1","date":"2016-03-11T01:14:00+01:00","text":"Fast shipping, adequate stealth. Product on point and is as pictured/described. Nice yellow powder DMT and some syrian rue!","prod_id":"/listing/1873/"},{"delivery_time":"3 days","note":"1","date":"2016-02-23T05:30:00+01:00","text":"quick shipping! came as described. thx!!","prod_id":"/listing/1873/"},{"delivery_time":"14 days","note":"1","date":"2016-02-13T02:43:00+01:00","text":"Quick delivery time (oceania), product tested, packaging discreet, vendor helpful. All round successful transaction. Thanks Hood!","prod_id":"/listing/1873/"},{"delivery_time":"5 days","note":"1","date":"2016-01-26T00:46:00+01:00","text":"Very great vendor. He is quick on reply and answered many of our questions. Will definately be back and would definately recommend. Product is a great experience as well. Thanks Hood","prod_id":"/listing/1873/"},{"delivery_time":"5 days","note":"1","date":"2016-01-21T00:55:00+01:00","text":"---","prod_id":"/listing/1873/"},{"delivery_time":"Not specified","note":"1","date":"2016-01-17T23:32:00+01:00","text":"Communication is great with this vendor. Finalized early due to positive feedback and bitcoin volatility. I have faith product will arrive. Will update if wrong.","prod_id":"/listing/1873/"},{"delivery_time":"7 days","note":"1","date":"2016-01-07T14:01:00+01:00","text":"---","prod_id":"/listing/1873/"},{"delivery_time":"Not specified","note":"1","date":"2016-01-07T01:09:00+01:00","text":"very honest vendor and ridicuously excellent stealth and fast replies A+++ definitely buying more from him","prod_id":"/listing/1873/"},{"delivery_time":"Not specified","note":"1","date":"2015-12-22T19:39:00+01:00","text":"Great vendor! Went above and beyond.","prod_id":"/listing/1873/"},{"delivery_time":"Not specified","note":"1","date":"2015-12-12T06:28:00+01:00","text":"A consummate professional. Safe packaging, quality product. Passionate about his work (for good reason, these are important tools) and it shows!","prod_id":"/listing/1873/"},{"delivery_time":"5 days","note":"1","date":"2015-11-21T10:05:00+01:00","text":"First review so I'll make it detailed for Hood:\n\nProduct was not the same consistency as the stuff I tried and the smell was much more mellow. This stuff is crystally, rolls around easily on paper/etc. \n\nTried 50mg on a dabber wow hit me HARD -- strong fractals, very strong trip zero complaints. \n\nHood had EXCELLENT communication through the whole transaction and weight was a couple mg over and the bonus was included as promised on the listing. Really no issues here, will do business again THANKS HOOD","prod_id":"/listing/1873/"},{"delivery_time":"Not specified","note":"1","date":"2016-06-26T19:08:00+02:00","text":"---","prod_id":"/listing/2286/"},{"delivery_time":"5 days","note":"1","date":"2016-05-02T06:40:00+02:00","text":"Second time legit in a row. Keep up the work, Hood.","prod_id":"/listing/2286/"},{"delivery_time":"5 days","note":"1","date":"2016-04-27T06:26:00+02:00","text":"Had a great experience and great product!  I'm not too experienced, but had any questions answered.  Great experience overall!","prod_id":"/listing/2286/"},{"delivery_time":"5 days","note":"1","date":"2016-04-23T03:54:00+02:00","text":"Trustworthy and professional. Great vendor!","prod_id":"/listing/2286/"},{"delivery_time":"Not specified","note":"1","date":"2016-04-22T17:25:00+02:00","text":"---","prod_id":"/listing/2286/"},{"delivery_time":"Not specified","note":"1","date":"2016-04-19T07:29:00+02:00","text":"---","prod_id":"/listing/2286/"},{"delivery_time":"4 days","note":"1","date":"2016-04-18T23:41:00+02:00","text":"Delivery speed exceeded expectations, but not as much as the product did. Would highly recommend to anyone in the market for DMT. Between the prices, quality, shipping, stealth, and professionalism of the vendor this is not an opportunity you'll want to pass up","prod_id":"/listing/2286/"},{"delivery_time":"3 days","note":"1","date":"2016-04-02T05:06:00+02:00","text":"super legit, good communication, nice delivery","prod_id":"/listing/2286/"},{"delivery_time":"7 days","note":"1","date":"2016-03-01T16:35:00+01:00","text":"Product is most definitely legit! Thanks!","prod_id":"/listing/2286/"},{"delivery_time":"12 days","note":"1","date":"2016-02-18T21:54:00+01:00","text":"Delivery took a strangely long time, but that was USPS, not Hood. Hood reached out and is clearly a vendor who cares. Haven't sampled the goods yet. Can't hardly wait - Thanks, Hood!","prod_id":"/listing/2286/"},{"delivery_time":"6 days","note":"1","date":"2016-02-14T22:58:00+01:00","text":"Great order. Exactly as described! Shipped next day. 6 days to East Coast.","prod_id":"/listing/2286/"},{"delivery_time":"Not specified","note":"1","date":"2016-02-12T03:16:00+01:00","text":"Fantastic Product, Great Stealth!","prod_id":"/listing/2286/"},{"delivery_time":"3 days","note":"1","date":"2016-01-30T05:48:00+01:00","text":"Superfast and responsive!","prod_id":"/listing/2286/"},{"delivery_time":"2 days","note":"1","date":"2016-01-20T03:44:00+01:00","text":"Lightning fast shipping. Great packaging.","prod_id":"/listing/2286/"},{"delivery_time":"Not specified","note":"1","date":"2016-01-02T21:25:00+01:00","text":"---","prod_id":"/listing/2286/"},{"delivery_time":"Not specified","note":"1","date":"2015-11-21T20:27:00+01:00","text":"Responsible Human Being","prod_id":"/listing/2286/"},{"delivery_time":"4 days","note":"1","date":"2015-11-21T19:24:00+01:00","text":"Great vendor and great product will be using again","prod_id":"/listing/2286/"},{"delivery_time":"3 days","note":"1","date":"2015-11-21T17:23:00+01:00","text":"5/5 Excellent! Perfect order with Fast delivery. You can feel good about hood!","prod_id":"/listing/2286/"},{"delivery_time":"Not specified","note":"1","date":"2016-06-12T23:54:00+02:00","text":"---","prod_id":"/listing/2287/"},{"delivery_time":"Not specified","note":"1","date":"2016-06-11T03:19:00+02:00","text":"Very Stealth. Good dealer. Will buy again.","prod_id":"/listing/2287/"},{"delivery_time":"Not specified","note":"1","date":"2016-04-06T13:32:00+02:00","text":"great product, shipping was fast.  exactly what I wanted.  great vendor.","prod_id":"/listing/2287/"},{"delivery_time":"3 days","note":"1","date":"2016-01-21T05:57:00+01:00","text":"arrived on time.","prod_id":"/listing/2287/"},{"delivery_time":"3 days","note":"1","date":"2015-12-25T04:03:00+01:00","text":"Vendor was able to handle the large quantity like a pro. Excellent quality product, and the vacuum sealing is a welcome bonus.","prod_id":"/listing/2291/"},{"delivery_time":"Not specified","note":"1","date":"2016-03-10T06:28:00+01:00","text":"Top bloke, insane delivery time (international), consistent, lovely product, hit Hood up for a fun time!","prod_id":"/listing/2290/"},{"delivery_time":"Not specified","note":"1","date":"2016-02-24T19:14:00+01:00","text":"---","prod_id":"/listing/2290/"},{"delivery_time":"Not specified","note":"1","date":"2015-12-06T14:17:00+01:00","text":"Perfect transaction all around - thank you Hood!","prod_id":"/listing/2290/"},{"delivery_time":"5 days","note":"1","date":"2016-03-12T23:48:00+01:00","text":"Wow!!  That doesn't even cover it.  Be careful oh my brothers and sisters because this is the genuine article like I've never experienced before. This vendor ain't messin' around.  You'd better be ready for a ride.","prod_id":"/listing/9753/"}]},"x":59.2306040148881,"y":47.8161558470631,"hidden":false,"read_cam0:size":7.999999999999999,"read_cam0:x":162.91810211977864,"read_cam0:y":212.89489684137797,"renderer1:x":820.6541847191611,"renderer1:y":554.0394784489616,"renderer1:size":6.485657578578983,"fa2_x":59.30570602416992,"fa2_y":47.87651062011719},{"id":"/listing/1873/","label":"1 Gram DMT + .5 Gram Syrian Rue","color":"#9e9e9e","type":"diamond","size":2.0766999999999993,"metadata":{"category":"product","product_id":"/listing/1873/","price_usd":"USD 85.00","price_btc":"0.1093","delivery":"United States","product_type":"Drugs/Psychedelics/DMT","vendor":"Hood","transactions":[{"delivery_time":"4 days","note":"1","date":"2016-06-15T18:29:00+02:00","text":"---","prod_id":"/listing/1873/"},{"delivery_time":"3 days","note":"1","date":"2016-06-13T00:31:00+02:00","text":"Fast, discreet, product as described. Great vendor.","prod_id":"/listing/1873/"},{"delivery_time":"Not specified","note":"1","date":"2016-05-16T07:27:00+02:00","text":"Great product. Thanks!","prod_id":"/listing/1873/"},{"delivery_time":"3 days","note":"1","date":"2016-05-05T21:29:00+02:00","text":"Very good quality and stealth!","prod_id":"/listing/1873/"},{"delivery_time":"10 days","note":"1","date":"2016-05-03T03:50:00+02:00","text":"Communication: N/A. Speed: 4/5. Stealth: 4/5. Product: 5/5.","prod_id":"/listing/1873/"},{"delivery_time":"4 days","note":"1","date":"2016-04-22T20:23:00+02:00","text":"---","prod_id":"/listing/1873/"},{"delivery_time":"5 days","note":"1","date":"2016-04-18T00:54:00+02:00","text":"---","prod_id":"/listing/1873/"},{"delivery_time":"7 days","note":"1","date":"2016-04-12T00:59:00+02:00","text":"---","prod_id":"/listing/1873/"},{"delivery_time":"3 days","note":"1","date":"2016-03-11T01:14:00+01:00","text":"Fast shipping, adequate stealth. Product on point and is as pictured/described. Nice yellow powder DMT and some syrian rue!","prod_id":"/listing/1873/"},{"delivery_time":"3 days","note":"1","date":"2016-02-23T05:30:00+01:00","text":"quick shipping! came as described. thx!!","prod_id":"/listing/1873/"},{"delivery_time":"14 days","note":"1","date":"2016-02-13T02:43:00+01:00","text":"Quick delivery time (oceania), product tested, packaging discreet, vendor helpful. All round successful transaction. Thanks Hood!","prod_id":"/listing/1873/"},{"delivery_time":"5 days","note":"1","date":"2016-01-26T00:46:00+01:00","text":"Very great vendor. He is quick on reply and answered many of our questions. Will definately be back and would definately recommend. Product is a great experience as well. Thanks Hood","prod_id":"/listing/1873/"},{"delivery_time":"5 days","note":"1","date":"2016-01-21T00:55:00+01:00","text":"---","prod_id":"/listing/1873/"},{"delivery_time":"Not specified","note":"1","date":"2016-01-17T23:32:00+01:00","text":"Communication is great with this vendor. Finalized early due to positive feedback and bitcoin volatility. I have faith product will arrive. Will update if wrong.","prod_id":"/listing/1873/"},{"delivery_time":"7 days","note":"1","date":"2016-01-07T14:01:00+01:00","text":"---","prod_id":"/listing/1873/"},{"delivery_time":"Not specified","note":"1","date":"2016-01-07T01:09:00+01:00","text":"very honest vendor and ridicuously excellent stealth and fast replies A+++ definitely buying more from him","prod_id":"/listing/1873/"},{"delivery_time":"Not specified","note":"1","date":"2015-12-22T19:39:00+01:00","text":"Great vendor! Went above and beyond.","prod_id":"/listing/1873/"},{"delivery_time":"Not specified","note":"1","date":"2015-12-12T06:28:00+01:00","text":"A consummate professional. Safe packaging, quality product. Passionate about his work (for good reason, these are important tools) and it shows!","prod_id":"/listing/1873/"},{"delivery_time":"5 days","note":"1","date":"2015-11-21T10:05:00+01:00","text":"First review so I'll make it detailed for Hood:\n\nProduct was not the same consistency as the stuff I tried and the smell was much more mellow. This stuff is crystally, rolls around easily on paper/etc. \n\nTried 50mg on a dabber wow hit me HARD -- strong fractals, very strong trip zero complaints. \n\nHood had EXCELLENT communication through the whole transaction and weight was a couple mg over and the bonus was included as promised on the listing. Really no issues here, will do business again THANKS HOOD","prod_id":"/listing/1873/"}]},"x":56.513229950528185,"y":-20.26268050826689,"hidden":false,"read_cam0:size":3.6418718764198093,"read_cam0:x":156.58551974475955,"read_cam0:y":54.24362947634525,"renderer1:x":816.4921192716241,"renderer1:y":449.76654222743025,"renderer1:size":2.952491741939475,"fa2_x":56.58366775512695,"fa2_y":-20.288219451904297},{"id":"/listing/2286/","label":".5 Gram DMT + .5 Gram Syrian Rue","color":"#9e9e9e","type":"diamond","size":1.2726,"metadata":{"category":"product","product_id":"/listing/2286/","price_usd":"USD 55.00","price_btc":"0.0707","delivery":"United States","product_type":"Drugs/Psychedelics/DMT","vendor":"Hood","transactions":[{"delivery_time":"Not specified","note":"1","date":"2016-06-26T19:08:00+02:00","text":"---","prod_id":"/listing/2286/"},{"delivery_time":"5 days","note":"1","date":"2016-05-02T06:40:00+02:00","text":"Second time legit in a row. Keep up the work, Hood.","prod_id":"/listing/2286/"},{"delivery_time":"5 days","note":"1","date":"2016-04-27T06:26:00+02:00","text":"Had a great experience and great product!  I'm not too experienced, but had any questions answered.  Great experience overall!","prod_id":"/listing/2286/"},{"delivery_time":"5 days","note":"1","date":"2016-04-23T03:54:00+02:00","text":"Trustworthy and professional. Great vendor!","prod_id":"/listing/2286/"},{"delivery_time":"Not specified","note":"1","date":"2016-04-22T17:25:00+02:00","text":"---","prod_id":"/listing/2286/"},{"delivery_time":"Not specified","note":"1","date":"2016-04-19T07:29:00+02:00","text":"---","prod_id":"/listing/2286/"},{"delivery_time":"4 days","note":"1","date":"2016-04-18T23:41:00+02:00","text":"Delivery speed exceeded expectations, but not as much as the product did. Would highly recommend to anyone in the market for DMT. Between the prices, quality, shipping, stealth, and professionalism of the vendor this is not an opportunity you'll want to pass up","prod_id":"/listing/2286/"},{"delivery_time":"3 days","note":"1","date":"2016-04-02T05:06:00+02:00","text":"super legit, good communication, nice delivery","prod_id":"/listing/2286/"},{"delivery_time":"7 days","note":"1","date":"2016-03-01T16:35:00+01:00","text":"Product is most definitely legit! Thanks!","prod_id":"/listing/2286/"},{"delivery_time":"12 days","note":"1","date":"2016-02-18T21:54:00+01:00","text":"Delivery took a strangely long time, but that was USPS, not Hood. Hood reached out and is clearly a vendor who cares. Haven't sampled the goods yet. Can't hardly wait - Thanks, Hood!","prod_id":"/listing/2286/"},{"delivery_time":"6 days","note":"1","date":"2016-02-14T22:58:00+01:00","text":"Great order. Exactly as described! Shipped next day. 6 days to East Coast.","prod_id":"/listing/2286/"},{"delivery_time":"Not specified","note":"1","date":"2016-02-12T03:16:00+01:00","text":"Fantastic Product, Great Stealth!","prod_id":"/listing/2286/"},{"delivery_time":"3 days","note":"1","date":"2016-01-30T05:48:00+01:00","text":"Superfast and responsive!","prod_id":"/listing/2286/"},{"delivery_time":"2 days","note":"1","date":"2016-01-20T03:44:00+01:00","text":"Lightning fast shipping. Great packaging.","prod_id":"/listing/2286/"},{"delivery_time":"Not specified","note":"1","date":"2016-01-02T21:25:00+01:00","text":"---","prod_id":"/listing/2286/"},{"delivery_time":"Not specified","note":"1","date":"2015-11-21T20:27:00+01:00","text":"Responsible Human Being","prod_id":"/listing/2286/"},{"delivery_time":"4 days","note":"1","date":"2015-11-21T19:24:00+01:00","text":"Great vendor and great product will be using again","prod_id":"/listing/2286/"},{"delivery_time":"3 days","note":"1","date":"2015-11-21T17:23:00+01:00","text":"5/5 Excellent! Perfect order with Fast delivery. You can feel good about hood!","prod_id":"/listing/2286/"}]},"x":-0.5211200284285185,"y":0.5247392143871888,"hidden":false,"read_cam0:size":2.6189368468877787,"read_cam0:x":23.672379745211362,"read_cam0:y":102.68673838958603,"renderer1:x":729.135468421251,"renderer1:y":481.6055895289609,"renderer1:size":2.1231909511046836,"fa2_x":-0.5592039823532104,"fa2_y":0.5423513650894165},{"id":"/listing/2287/","label":"200mg DMT + 100mg Gram Syrian Rue","color":"#9e9e9e","type":"diamond","size":0.1284,"metadata":{"category":"product","product_id":"/listing/2287/","price_usd":"USD 25.00","price_btc":"0.0321","delivery":"United States","product_type":"Drugs/Psychedelics/DMT","vendor":"Hood","transactions":[{"delivery_time":"Not specified","note":"1","date":"2016-06-12T23:54:00+02:00","text":"---","prod_id":"/listing/2287/"},{"delivery_time":"Not specified","note":"1","date":"2016-06-11T03:19:00+02:00","text":"Very Stealth. Good dealer. Will buy again.","prod_id":"/listing/2287/"},{"delivery_time":"Not specified","note":"1","date":"2016-04-06T13:32:00+02:00","text":"great product, shipping was fast.  exactly what I wanted.  great vendor.","prod_id":"/listing/2287/"},{"delivery_time":"3 days","note":"1","date":"2016-01-21T05:57:00+01:00","text":"arrived on time.","prod_id":"/listing/2287/"}]},"x":100.72061139753202,"y":81.08952323421971,"hidden":false,"read_cam0:size":1.163343934575193,"read_cam0:x":259.60662687488303,"read_cam0:y":290.43532185572906,"renderer1:x":884.2023463102425,"renderer1:y":605.0026250181514,"renderer1:size":0.9431313007214367,"fa2_x":100.8497085571289,"fa2_y":81.19358825683594},{"id":"/listing/2290/","label":"3.5 Gram DMT + 2 Gram Syrian Rue","color":"#9e9e9e","type":"diamond","size":0.9642000000000001,"metadata":{"category":"product","product_id":"/listing/2290/","price_usd":"USD 250.00","price_btc":"0.3214","delivery":"United States","product_type":"Drugs/Psychedelics/DMT","vendor":"Hood","transactions":[{"delivery_time":"Not specified","note":"1","date":"2016-03-10T06:28:00+01:00","text":"Top bloke, insane delivery time (international), consistent, lovely product, hit Hood up for a fun time!","prod_id":"/listing/2290/"},{"delivery_time":"Not specified","note":"1","date":"2016-02-24T19:14:00+01:00","text":"---","prod_id":"/listing/2290/"},{"delivery_time":"Not specified","note":"1","date":"2015-12-06T14:17:00+01:00","text":"Perfect transaction all around - thank you Hood!","prod_id":"/listing/2290/"}]},"x":35.179345016690945,"y":54.86814610532766,"hidden":false,"read_cam0:size":2.226606088141754,"read_cam0:x":106.86892551704307,"read_cam0:y":229.32889089615358,"renderer1:x":783.816078637605,"renderer1:y":564.8406579314795,"renderer1:size":1.805125581258334,"fa2_x":35.22474670410156,"fa2_y":54.936614990234375},{"id":"/listing/2291/","label":"15 Gram DMT + 4 Gram Syrian Rue","color":"#9e9e9e","type":"diamond","size":0.8999,"metadata":{"category":"product","product_id":"/listing/2291/","price_usd":"USD 700.00","price_btc":"0.8999","delivery":"United States","product_type":"Drugs/Psychedelics/DMT","vendor":"Hood","transactions":[{"delivery_time":"3 days","note":"1","date":"2015-12-25T04:03:00+01:00","text":"Vendor was able to handle the large quantity like a pro. Excellent quality product, and the vacuum sealing is a welcome bonus.","prod_id":"/listing/2291/"}]},"x":70.72879730309586,"y":31.986524606171905,"hidden":false,"read_cam0:size":2.1448069059518406,"read_cam0:x":189.71355038597767,"read_cam0:y":176.0054434849696,"renderer1:x":838.26539019198,"renderer1:y":529.794026893699,"renderer1:size":1.738810395521887,"fa2_x":70.82019805908203,"fa2_y":32.028167724609375},{"id":"vendor-1","label":"vendor-1","color":"#00bcd4","type":"square","size":0.0242,"metadata":{"category":"vendor","transactions":[{"delivery_time":"7 days","note":"1","date":"2015-12-10T22:28:00+01:00","text":"First time that I smoked DMT and it was amazing! This product is absolutely awesome! VERY GOOD! I will buy again","prod_id":"/listing/2647/"}]},"x":-32.629195747802754,"y":-175.59079523375217,"hidden":false,"read_cam0:size":1.030786006360745,"read_cam0:x":-51.152443624912834,"read_cam0:y":-307.7338010719385,"renderer1:x":679.9571406042496,"renderer1:y":211.85826606881182,"renderer1:size":0.8356656342558413,"fa2_x":-32.67161560058594,"fa2_y":-175.81980895996094},{"id":"/listing/2647/","label":"250mg white n,n-DMT, 99.0% Purity! *Special price*","color":"#9e9e9e","type":"diamond","size":0.0242,"metadata":{"category":"product","product_id":"/listing/2647/","price_usd":"USD 18.79","price_btc":"0.0242","delivery":"United Kingdom","product_type":"Drugs/Psychedelics/DMT","vendor":"multiexciter","transactions":[{"delivery_time":"7 days","note":"1","date":"2015-12-10T22:28:00+01:00","text":"First time that I smoked DMT and it was amazing! This product is absolutely awesome! VERY GOOD! I will buy again","prod_id":"/listing/2647/"}]},"x":-37.289453694633075,"y":-175.7897862986496,"hidden":false,"read_cam0:size":1.030786006360745,"read_cam0:x":-62.01273250608009,"read_cam0:y":-308.1975308641976,"renderer1:x":672.8192574428891,"renderer1:y":211.55348144366917,"renderer1:size":0.8356656342558413,"fa2_x":-37.33800506591797,"fa2_y":-176.0183563232422},{"id":"vendor-2","label":"vendor-2","color":"#00bcd4","type":"square","size":1.0088000000000001,"metadata":{"category":"vendor","transactions":[{"delivery_time":"2 days","note":"1","date":"2016-09-14T13:11:00+02:00","text":"Unbelievably well done. Postage was super good too. Highly recommended. This was my first time and am impressed. Haven't product as of yet.","prod_id":"/listing/2665/"},{"delivery_time":"Next Day","note":"1","date":"2016-08-18T11:13:00+02:00","text":"legit and fast shipping a++","prod_id":"/listing/2665/"},{"delivery_time":"Next Day","note":"1","date":"2016-08-18T11:10:00+02:00","text":"legit and fast shipping a++","prod_id":"/listing/2665/"},{"delivery_time":"Same Day","note":"1","date":"2016-08-11T09:48:00+02:00","text":"fast cool stealthy shipping heaviest dmt trip i never broke threw this heavy injecting it lol I'll ordor again saturday thanks for the next level experience????","prod_id":"/listing/2665/"},{"delivery_time":"Next Day","note":"1","date":"2016-08-10T10:59:00+02:00","text":"Good service! Would recommend! 100mg is smaller than I thought though!","prod_id":"/listing/2665/"},{"delivery_time":"Not specified","note":"1","date":"2016-05-21T15:28:00+02:00","text":"---","prod_id":"/listing/2665/"},{"delivery_time":"Next Day","note":"1","date":"2016-05-14T05:31:00+02:00","text":"Top marks in every category, could not ask for better","prod_id":"/listing/2665/"},{"delivery_time":"2 days","note":"1","date":"2016-01-06T07:07:00+01:00","text":"Prompt response from vendor, very discreet packaging, free express shipping with tracking! Only need a little bit of this stuff to get all tingly :) Thank you, would buy again","prod_id":"/listing/2665/"},{"delivery_time":"Next Day","note":"1","date":"2016-11-01T16:49:00+01:00","text":"Arrived on time, as ordered.  Thanks.","prod_id":"/listing/2666/"},{"delivery_time":"2 days","note":"1","date":"2016-08-18T03:41:00+02:00","text":"---","prod_id":"/listing/2666/"},{"delivery_time":"2 days","note":"1","date":"2016-11-17T02:26:00+01:00","text":"Order arrived on time","prod_id":"/listing/2668/"},{"delivery_time":"Not specified","note":"1","date":"2016-04-29T13:57:00+02:00","text":"Great product, stealth and timely. Would order again without hesitation!","prod_id":"/listing/2668/"},{"delivery_time":"Not specified","note":"1","date":"2016-01-05T12:33:00+01:00","text":"Quick, great stealth, looks lovely, thank you!","prod_id":"/listing/2668/"},{"delivery_time":"2 days","note":"1","date":"2016-03-03T15:21:00+01:00","text":"Good stuff, great communication, thank you once again :-)","prod_id":"/listing/2667/"},{"delivery_time":"Not specified","note":"1","date":"2016-01-16T04:08:00+01:00","text":"---","prod_id":"/listing/2667/"},{"delivery_time":"2 days","note":"1","date":"2016-08-10T11:23:00+02:00","text":"As always, great stealth, quick delivery, top quality. A+","prod_id":"/listing/2670/"},{"delivery_time":"Next Day","note":"1","date":"2016-04-18T04:15:00+02:00","text":"Quick, stealth, love your work","prod_id":"/listing/2670/"}]},"x":-93.7582670791104,"y":69.43029570191246,"hidden":false,"read_cam0:size":2.2833439345751936,"read_cam0:x":-193.60794314227726,"read_cam0:y":263.26459856599394,"renderer1:x":586.3288106054533,"renderer1:y":587.1447714772482,"renderer1:size":1.851123361722495,"fa2_x":-93.87808227539062,"fa2_y":69.52287292480469},{"id":"/listing/2665/","label":"CHANGA 100mg 50% DMT (free express shipping)","color":"#9e9e9e","type":"diamond","size":0.152,"metadata":{"category":"product","product_id":"/listing/2665/","price_usd":"USD 14.81","price_btc":"0.0190","delivery":"Australia","product_type":"Drugs/Psychedelics/DMT","vendor":"skylerpinkman","transactions":[{"delivery_time":"2 days","note":"1","date":"2016-09-14T13:11:00+02:00","text":"Unbelievably well done. Postage was super good too. Highly recommended. This was my first time and am impressed. Haven't product as of yet.","prod_id":"/listing/2665/"},{"delivery_time":"Next Day","note":"1","date":"2016-08-18T11:13:00+02:00","text":"legit and fast shipping a++","prod_id":"/listing/2665/"},{"delivery_time":"Next Day","note":"1","date":"2016-08-18T11:10:00+02:00","text":"legit and fast shipping a++","prod_id":"/listing/2665/"},{"delivery_time":"Same Day","note":"1","date":"2016-08-11T09:48:00+02:00","text":"fast cool stealthy shipping heaviest dmt trip i never broke threw this heavy injecting it lol I'll ordor again saturday thanks for the next level experience????","prod_id":"/listing/2665/"},{"delivery_time":"Next Day","note":"1","date":"2016-08-10T10:59:00+02:00","text":"Good service! Would recommend! 100mg is smaller than I thought though!","prod_id":"/listing/2665/"},{"delivery_time":"Not specified","note":"1","date":"2016-05-21T15:28:00+02:00","text":"---","prod_id":"/listing/2665/"},{"delivery_time":"Next Day","note":"1","date":"2016-05-14T05:31:00+02:00","text":"Top marks in every category, could not ask for better","prod_id":"/listing/2665/"},{"delivery_time":"2 days","note":"1","date":"2016-01-06T07:07:00+01:00","text":"Prompt response from vendor, very discreet packaging, free express shipping with tracking! Only need a little bit of this stuff to get all tingly :) Thank you, would buy again","prod_id":"/listing/2665/"}]},"x":-106.2669411905962,"y":28.136876943430554,"hidden":false,"read_cam0:size":1.1933666515220356,"read_cam0:x":-222.75822107131575,"read_cam0:y":167.0342049430092,"renderer1:x":567.1699023797729,"renderer1:y":523.8977148134328,"renderer1:size":0.9674709334334144,"fa2_x":-106.40446472167969,"fa2_y":28.173282623291016},{"id":"/listing/2666/","label":"CHANGA 200mg 50% DMT (free express shipping)","color":"#9e9e9e","type":"diamond","size":0.0762,"metadata":{"category":"product","product_id":"/listing/2666/","price_usd":"USD 29.62","price_btc":"0.0381","delivery":"Australia","product_type":"Drugs/Psychedelics/DMT","vendor":"skylerpinkman","transactions":[{"delivery_time":"Next Day","note":"1","date":"2016-11-01T16:49:00+01:00","text":"Arrived on time, as ordered.  Thanks.","prod_id":"/listing/2666/"},{"delivery_time":"2 days","note":"1","date":"2016-08-18T03:41:00+02:00","text":"---","prod_id":"/listing/2666/"}]},"x":-82.50172356797786,"y":58.236519300274345,"hidden":false,"read_cam0:size":1.096937755565652,"read_cam0:x":-167.37563674870609,"read_cam0:y":237.1785649644275,"renderer1:x":603.5698932450704,"renderer1:y":569.999826068458,"renderer1:size":0.889295333451724,"fa2_x":-82.60737609863281,"fa2_y":58.313114166259766},{"id":"/listing/2667/","label":"CHANGA 300mg 50% DMT (free express shipping)","color":"#9e9e9e","type":"diamond","size":0.1142,"metadata":{"category":"product","product_id":"/listing/2667/","price_usd":"USD 44.44","price_btc":"0.0571","delivery":"Australia","product_type":"Drugs/Psychedelics/DMT","vendor":"skylerpinkman","transactions":[{"delivery_time":"2 days","note":"1","date":"2016-03-03T15:21:00+01:00","text":"Good stuff, great communication, thank you once again :-)","prod_id":"/listing/2667/"},{"delivery_time":"Not specified","note":"1","date":"2016-01-16T04:08:00+01:00","text":"---","prod_id":"/listing/2667/"}]},"x":-116.97685704395045,"y":69.86881566997613,"hidden":false,"read_cam0:size":1.1452794184461608,"read_cam0:x":-247.71666358403763,"read_cam0:y":264.2865277355093,"renderer1:x":550.7660618839395,"renderer1:y":587.8164304994899,"renderer1:size":0.9284862674794842,"fa2_x":-117.12606048583984,"fa2_y":69.96415710449219},{"id":"/listing/2668/","label":"CHANGA 500mg 50% DMT (free express shipping)","color":"#9e9e9e","type":"diamond","size":0.2856,"metadata":{"category":"product","product_id":"/listing/2668/","price_usd":"USD 74.06","price_btc":"0.0952","delivery":"Australia","product_type":"Drugs/Psychedelics/DMT","vendor":"skylerpinkman","transactions":[{"delivery_time":"2 days","note":"1","date":"2016-11-17T02:26:00+01:00","text":"Order arrived on time","prod_id":"/listing/2668/"},{"delivery_time":"Not specified","note":"1","date":"2016-04-29T13:57:00+02:00","text":"Great product, stealth and timely. Would order again without hesitation!","prod_id":"/listing/2668/"},{"delivery_time":"Not specified","note":"1","date":"2016-01-05T12:33:00+01:00","text":"Quick, great stealth, looks lovely, thank you!","prod_id":"/listing/2668/"}]},"x":-39.21584878546066,"y":69.70723513156318,"hidden":false,"read_cam0:size":1.3633257610177194,"read_cam0:x":-66.50201344811026,"read_cam0:y":263.9099796249197,"renderer1:x":669.86869478352,"renderer1:y":587.5689456998285,"renderer1:size":1.1052580067520665,"fa2_x":-39.26606750488281,"fa2_y":69.79663848876953},{"id":"/listing/2670/","label":"CHANGA 1 gram 50% DMT (free express shipping)","color":"#9e9e9e","type":"diamond","size":0.3808,"metadata":{"category":"product","product_id":"/listing/2670/","price_usd":"USD 148.12","price_btc":"0.1904","delivery":"Australia","product_type":"Drugs/Psychedelics/DMT","vendor":"skylerpinkman","transactions":[{"delivery_time":"2 days","note":"1","date":"2016-08-10T11:23:00+02:00","text":"As always, great stealth, quick delivery, top quality. A+","prod_id":"/listing/2670/"},{"delivery_time":"Next Day","note":"1","date":"2016-04-18T04:15:00+02:00","text":"Quick, stealth, love your work","prod_id":"/listing/2670/"}]},"x":-108.30225867267258,"y":83.77611300420688,"hidden":false,"read_cam0:size":1.4844343480236257,"read_cam0:x":-227.50133530928912,"read_cam0:y":296.6961643541779,"renderer1:x":564.0525087614183,"renderer1:y":609.1175397073088,"renderer1:size":1.2034416098952976,"fa2_x":-108.44020080566406,"fa2_y":83.89033508300781},{"id":"vendor-3","label":"vendor-3","color":"#00bcd4","type":"square","size":0.3457,"metadata":{"category":"vendor","transactions":[{"delivery_time":"Not specified","note":"1","date":"2016-08-18T18:01:00+02:00","text":"Order arrived quickly and overall very positive experience with vendor.","prod_id":"/listing/3421/"},{"delivery_time":"Not specified","note":"1","date":"2016-05-04T04:53:00+02:00","text":"Received item today! Looks legit. Eagerly awaiting the right time to dive in :)","prod_id":"/listing/3421/"},{"delivery_time":"Same Day","note":"1","date":"2016-04-28T10:39:00+02:00","text":"Fast delivery.","prod_id":"/listing/3421/"},{"delivery_time":"Next Day","note":"1","date":"2016-04-01T01:14:00+02:00","text":"Great Product!","prod_id":"/listing/3424/"},{"delivery_time":"3 days","note":"1","date":"2016-08-31T22:10:00+02:00","text":"Came sooner than expected and everything is what it should be. Can't wait to try it all. Awesome vendor will order from again.","prod_id":"/listing/3430/"}]},"x":-39.20281388259803,"y":-109.2495439944204,"hidden":false,"read_cam0:size":1.4397819173103137,"read_cam0:x":-66.4716368440164,"read_cam0:y":-153.13181092088323,"renderer1:x":669.8886596899082,"renderer1:y":313.4698303915302,"renderer1:size":1.1672415629380768,"fa2_x":-39.25320053100586,"fa2_y":-109.3970718383789},{"id":"/listing/3421/","label":"Ayahuasca DMT One Person Kit","color":"#9e9e9e","type":"diamond","size":0.1272,"metadata":{"category":"product","product_id":"/listing/3421/","price_usd":"USD 33.00","price_btc":"0.0424","delivery":"Worldwide","product_type":"Drugs/Psychedelics/DMT","vendor":"DonPericos","transactions":[{"delivery_time":"Not specified","note":"1","date":"2016-08-18T18:01:00+02:00","text":"Order arrived quickly and overall very positive experience with vendor.","prod_id":"/listing/3421/"},{"delivery_time":"Not specified","note":"1","date":"2016-05-04T04:53:00+02:00","text":"Received item today! Looks legit. Eagerly awaiting the right time to dive in :)","prod_id":"/listing/3421/"},{"delivery_time":"Same Day","note":"1","date":"2016-04-28T10:39:00+02:00","text":"Fast delivery.","prod_id":"/listing/3421/"}]},"x":-14.325056323636879,"y":-116.45658499089927,"hidden":false,"read_cam0:size":1.1618173557473876,"read_cam0:x":-8.496383781098842,"read_cam0:y":-169.9271360065712,"renderer1:x":707.9926721283814,"renderer1:y":302.43116747653215,"renderer1:size":0.941893692278455,"fa2_x":-14.344698905944824,"fa2_y":-116.61018371582031},{"id":"/listing/3424/","label":"Ayahuasca DMT Three Person Kit","color":"#9e9e9e","type":"diamond","size":0.1028,"metadata":{"category":"product","product_id":"/listing/3424/","price_usd":"USD 80.00","price_btc":"0.1028","delivery":"Worldwide","product_type":"Drugs/Psychedelics/DMT","vendor":"DonPericos","transactions":[{"delivery_time":"Next Day","note":"1","date":"2016-04-01T01:14:00+02:00","text":"Great Product!","prod_id":"/listing/3424/"}]},"x":-43.435850237612314,"y":-97.529633076963,"hidden":false,"read_cam0:size":1.1307769195820083,"read_cam0:x":-76.3363263492843,"read_cam0:y":-125.81967076097983,"renderer1:x":663.4051303950472,"renderer1:y":331.4206296272811,"renderer1:size":0.9167289872711563,"fa2_x":-43.491973876953125,"fa2_y":-97.66505432128906},{"id":"/listing/3430/","label":"NATURES BEST - SUPER TRIO!!! - MESCALINE, PSILOCYBIN, DMT!!!","color":"#9e9e9e","type":"diamond","size":0.1157,"metadata":{"category":"product","product_id":"/listing/3430/","price_usd":"USD 90.00","price_btc":"0.1157","delivery":"Worldwide","product_type":"Drugs/Psychedelics/DMT","vendor":"DonPericos","transactions":[{"delivery_time":"3 days","note":"1","date":"2016-08-31T22:10:00+02:00","text":"Came sooner than expected and everything is what it should be. Can't wait to try it all. Awesome vendor will order from again.","prod_id":"/listing/3430/"}]},"x":-53.518361988202365,"y":-113.45222346660374,"hidden":false,"read_cam0:size":1.1471876419809177,"read_cam0:x":-99.83266314189623,"read_cam0:y":-162.92575659161727,"renderer1:x":647.9622532689635,"renderer1:y":307.03279721024546,"renderer1:size":0.9300332780332116,"fa2_x":-53.587242126464844,"fa2_y":-113.60455322265625},{"id":"vendor-4","label":"vendor-4","color":"#00bcd4","type":"square","size":0.0707,"metadata":{"category":"vendor","transactions":[{"delivery_time":"Not specified","note":"1","date":"2016-03-24T15:00:00+01:00","text":"---","prod_id":"/listing/8371/"}]},"x":-131.6129444994056,"y":-72.13914439556831,"hidden":false,"read_cam0:size":1.08994093593821,"read_cam0:x":-281.8246764171862,"read_cam0:y":-66.64954647601313,"renderer1:x":528.3487014312745,"renderer1:y":370.30996658789,"renderer1:size":0.8836229614213902,"fa2_x":-131.78675842285156,"fa2_y":-72.23575592041016},{"id":"/listing/8371/","label":"500mg aMT (alpha-methyl-tryptamine) succinate","color":"#9e9e9e","type":"diamond","size":0.0707,"metadata":{"category":"product","product_id":"/listing/8371/","price_usd":"USD 55.00","price_btc":"0.0707","delivery":"United States","product_type":"Drugs/Psychedelics/DMT","vendor":"seedofchaos","transactions":[{"delivery_time":"Not specified","note":"1","date":"2016-03-24T15:00:00+01:00","text":"---","prod_id":"/listing/8371/"}]},"x":-129.64750506147087,"y":-76.32559177543108,"hidden":false,"read_cam0:size":1.08994093593821,"read_cam0:x":-277.244406329577,"read_cam0:y":-76.40566479603856,"renderer1:x":531.359066357158,"renderer1:y":363.8977952875935,"renderer1:size":0.8836229614213902,"fa2_x":-129.81881713867188,"fa2_y":-76.42811584472656},{"id":"vendor-5","label":"vendor-5","color":"#00bcd4","type":"square","size":0.3277999999999999,"metadata":{"category":"vendor","transactions":[{"delivery_time":"Not specified","note":"1","date":"2016-10-10T12:16:00+02:00","text":"---","prod_id":"/listing/9350/"},{"delivery_time":"Not specified","note":"1","date":"2016-10-19T10:11:00+02:00","text":"---","prod_id":"/listing/9351/"},{"delivery_time":"Not specified","note":"1","date":"2016-09-22T06:44:00+02:00","text":"As Rx'd. Excellent vendor!!!","prod_id":"/listing/9351/"},{"delivery_time":"Not specified","note":"1","date":"2016-08-08T09:53:00+02:00","text":"legit fast stealthy shipping will be a returning customer","prod_id":"/listing/9351/"},{"delivery_time":"3 days","note":"1","date":"2016-05-30T04:30:00+02:00","text":"---","prod_id":"/listing/9351/"}]},"x":-53.7323947973267,"y":-16.281229391204448,"hidden":false,"read_cam0:size":1.4170104497955476,"read_cam0:x":-100.33144629159698,"read_cam0:y":63.52202346029923,"renderer1:x":647.6344299592547,"renderer1:y":455.86473104240537,"renderer1:size":1.1487805703302634,"fa2_x":-53.80221176147461,"fa2_y":-16.3038330078125},{"id":"/listing/9350/","label":"DMT 500Mg  >> Same day post","color":"#9e9e9e","type":"diamond","size":0.1478,"metadata":{"category":"product","product_id":"/listing/9350/","price_usd":"USD 115.00","price_btc":"0.1478","delivery":"Australia","product_type":"Drugs/Psychedelics/DMT","vendor":"HangAbout","transactions":[{"delivery_time":"Not specified","note":"1","date":"2016-10-10T12:16:00+02:00","text":"---","prod_id":"/listing/9350/"}]},"x":-47.26930608749135,"y":-18.874929813495807,"hidden":false,"read_cam0:size":1.188023625624716,"read_cam0:x":-85.26983140799103,"read_cam0:y":57.47765077134789,"renderer1:x":657.533618501745,"renderer1:y":451.89209030425076,"renderer1:size":0.9631393038829776,"fa2_x":-47.332096099853516,"fa2_y":-18.901504516601562},{"id":"/listing/9351/","label":"DMT 100Mg  >> Same day Free post","color":"#9e9e9e","type":"diamond","size":0.18,"metadata":{"category":"product","product_id":"/listing/9351/","price_usd":"USD 35.00","price_btc":"0.0450","delivery":"Australia","product_type":"Drugs/Psychedelics/DMT","vendor":"HangAbout","transactions":[{"delivery_time":"Not specified","note":"1","date":"2016-10-19T10:11:00+02:00","text":"---","prod_id":"/listing/9351/"},{"delivery_time":"Not specified","note":"1","date":"2016-09-22T06:44:00+02:00","text":"As Rx'd. Excellent vendor!!!","prod_id":"/listing/9351/"},{"delivery_time":"Not specified","note":"1","date":"2016-08-08T09:53:00+02:00","text":"legit fast stealthy shipping will be a returning customer","prod_id":"/listing/9351/"},{"delivery_time":"3 days","note":"1","date":"2016-05-30T04:30:00+02:00","text":"---","prod_id":"/listing/9351/"}]},"x":-65.24460325745758,"y":-24.054507258241255,"hidden":false,"read_cam0:size":1.2289868241708315,"read_cam0:x":-127.15955558590666,"read_cam0:y":45.407137084316176,"renderer1:x":630.0017581511352,"renderer1:y":443.958791536753,"renderer1:size":0.9963484637696587,"fa2_x":-65.32759094238281,"fa2_y":-24.085342407226562},{"id":"/listing/9753/","label":"1 Gram Large Crystal Growth DMT + MAOI","color":"#9e9e9e","type":"diamond","size":0.1607,"metadata":{"category":"product","product_id":"/listing/9753/","price_usd":"USD 125.00","price_btc":"0.1607","delivery":"United States","product_type":"Drugs/Psychedelics/DMT","vendor":"Hood","transactions":[{"delivery_time":"5 days","note":"1","date":"2016-03-12T23:48:00+01:00","text":"Wow!!  That doesn't even cover it.  Be careful oh my brothers and sisters because this is the genuine article like I've never experienced before. This vendor ain't messin' around.  You'd better be ready for a ride.","prod_id":"/listing/9753/"}]},"x":59.38157332610407,"y":72.99198357668664,"hidden":false,"read_cam0:size":1.2044343480236257,"read_cam0:x":163.26992177240353,"read_cam0:y":271.56477414981697,"renderer1:x":820.8854168347876,"renderer1:y":592.600030005301,"renderer1:size":0.9764435946450332,"fa2_x":59.457855224609375,"fa2_y":73.08489227294922},{"id":"P***g","label":"P***g","size":0.1093,"metadata":{"category":"client","transactions":[{"delivery_time":"4 days","note":"1","date":"2016-06-15T18:29:00+02:00","text":"---","prod_id":"/listing/1873/"}]},"x":43.565332753202824,"y":-30.654200117834616,"color":"#ffc107","hidden":false,"read_cam0:size":1.1390458882326215,"read_cam0:x":126.41167409695574,"read_cam0:y":30.027179193592495,"renderer1:x":796.6604750934999,"renderer1:y":433.85037327533837,"renderer1:size":0.9234326996706415,"fa2_x":43.620643615722656,"fa2_y":-30.693626403808594},{"id":"s***w","label":"s***w","size":0.1093,"metadata":{"category":"client","transactions":[{"delivery_time":"3 days","note":"1","date":"2016-06-13T00:31:00+02:00","text":"Fast, discreet, product as described. Great vendor.","prod_id":"/listing/1873/"}]},"x":64.07748008118139,"y":-7.038231534088657,"color":"#ffc107","hidden":false,"read_cam0:size":1.1390458882326215,"read_cam0:x":174.2132868180769,"read_cam0:y":85.06195279501816,"renderer1:x":828.0779014862399,"renderer1:y":470.02176687980375,"renderer1:size":0.9234326996706415,"fa2_x":64.157958984375,"fa2_y":-7.047512531280518},{"id":"r***e","label":"r***e","size":0.2186,"metadata":{"category":"client","transactions":[{"delivery_time":"Not specified","note":"1","date":"2016-05-16T07:27:00+02:00","text":"Great product. Thanks!","prod_id":"/listing/1873/"},{"delivery_time":"3 days","note":"1","date":"2016-02-23T05:30:00+01:00","text":"quick shipping! came as described. thx!!","prod_id":"/listing/1873/"}]},"x":71.99479945027524,"y":-34.16140117187307,"color":"#ffc107","hidden":false,"read_cam0:size":1.278091776465243,"read_cam0:x":192.66384824489714,"read_cam0:y":21.853979974631173,"renderer1:x":840.2044621299924,"renderer1:y":428.47856947547496,"renderer1:size":1.03615820201891,"fa2_x":72.08590698242188,"fa2_y":-34.20412826538086},{"id":"s***e","label":"s***e","size":0.20450000000000002,"metadata":{"category":"client","transactions":[{"delivery_time":"3 days","note":"1","date":"2016-05-05T21:29:00+02:00","text":"Very good quality and stealth!","prod_id":"/listing/1873/"},{"delivery_time":"Not specified","note":"1","date":"2016-04-29T13:57:00+02:00","text":"Great product, stealth and timely. Would order again without hesitation!","prod_id":"/listing/2668/"}]},"x":-9.969229390474124,"y":44.976811375899786,"color":"#ffc107","hidden":false,"read_cam0:size":1.260154475238528,"read_cam0:x":1.6544575135748252,"read_cam0:y":206.27807400843759,"renderer1:x":714.6642735879465,"renderer1:y":549.6905970519988,"renderer1:size":1.0216163028138727,"fa2_x":-9.983014106750488,"fa2_y":45.033390045166016},{"id":"d***3","label":"d***3","size":0.1093,"metadata":{"category":"client","transactions":[{"delivery_time":"10 days","note":"1","date":"2016-05-03T03:50:00+02:00","text":"Communication: N/A. Speed: 4/5. Stealth: 4/5. Product: 5/5.","prod_id":"/listing/1873/"}]},"x":40.084825642181386,"y":-22.136474440486218,"color":"#ffc107","hidden":false,"read_cam0:size":1.1390458882326215,"read_cam0:x":118.30068257890919,"read_cam0:y":49.87693054254025,"renderer1:x":791.3295570661721,"renderer1:y":446.89654612222654,"renderer1:size":0.9234326996706415,"fa2_x":40.13597106933594,"fa2_y":-22.163711547851562},{"id":"m***e","label":"m***e","size":0.1093,"metadata":{"category":"client","transactions":[{"delivery_time":"4 days","note":"1","date":"2016-04-22T20:23:00+02:00","text":"---","prod_id":"/listing/1873/"}]},"x":45.8822127449863,"y":-45.78707719940662,"color":"#ffc107","hidden":false,"read_cam0:size":1.1390458882326215,"read_cam0:x":131.81094304319055,"read_cam0:y":-5.2385547173057825,"renderer1:x":800.2091238740877,"renderer1:y":410.672105090214,"renderer1:size":0.9234326996706415,"fa2_x":45.940399169921875,"fa2_y":-45.84531021118164},{"id":"W***o","label":"W***o","size":0.1093,"metadata":{"category":"client","transactions":[{"delivery_time":"5 days","note":"1","date":"2016-04-18T00:54:00+02:00","text":"---","prod_id":"/listing/1873/"}]},"x":74.64414365759531,"y":-14.156960069473902,"color":"#ffc107","hidden":false,"read_cam0:size":1.1390458882326215,"read_cam0:x":198.83789349419771,"read_cam0:y":68.47243151895319,"renderer1:x":844.2623296604668,"renderer1:y":459.1183677283506,"renderer1:size":0.9234326996706415,"fa2_x":74.73786926269531,"fa2_y":-14.175165176391602},{"id":"w***u","label":"w***u","size":0.1093,"metadata":{"category":"client","transactions":[{"delivery_time":"7 days","note":"1","date":"2016-04-12T00:59:00+02:00","text":"---","prod_id":"/listing/1873/"}]},"x":62.27396511493799,"y":-38.47761748929721,"color":"#ffc107","hidden":false,"read_cam0:size":1.1390458882326215,"read_cam0:x":170.01036634492286,"read_cam0:y":11.795447460842654,"renderer1:x":825.3155481453553,"renderer1:y":421.8676376076616,"renderer1:size":0.9234326996706415,"fa2_x":62.35310745239258,"fa2_y":-38.52671813964844},{"id":"G***5","label":"G***5","size":0.1093,"metadata":{"category":"client","transactions":[{"delivery_time":"3 days","note":"1","date":"2016-03-11T01:14:00+01:00","text":"Fast shipping, adequate stealth. Product on point and is as pictured/described. Nice yellow powder DMT and some syrian rue!","prod_id":"/listing/1873/"}]},"x":58.44932622740659,"y":-48.473784554259595,"color":"#ffc107","hidden":false,"read_cam0:size":1.1390458882326215,"read_cam0:x":161.09740838022725,"read_cam0:y":-11.49967123612548,"renderer1:x":819.4575407506868,"renderer1:y":406.55701030222014,"renderer1:size":0.9234326996706415,"fa2_x":58.5236701965332,"fa2_y":-48.53535079956055},{"id":"A***1","label":"A***1","size":0.4307,"metadata":{"category":"client","transactions":[{"delivery_time":"14 days","note":"1","date":"2016-02-13T02:43:00+01:00","text":"Quick delivery time (oceania), product tested, packaging discreet, vendor helpful. All round successful transaction. Thanks Hood!","prod_id":"/listing/1873/"},{"delivery_time":"Not specified","note":"1","date":"2016-03-10T06:28:00+01:00","text":"Top bloke, insane delivery time (international), consistent, lovely product, hit Hood up for a fun time!","prod_id":"/listing/2290/"}]},"x":39.645061425479376,"y":26.070459393436973,"color":"#ffc107","hidden":false,"read_cam0:size":1.547914584279873,"read_cam0:x":117.27585380602282,"read_cam0:y":162.21861494818754,"renderer1:x":790.65599229075,"renderer1:y":520.7326867822117,"renderer1:size":1.2549054943159619,"fa2_x":39.69447326660156,"fa2_y":26.10238265991211},{"id":"H***7","label":"H***7","size":0.1093,"metadata":{"category":"client","transactions":[{"delivery_time":"5 days","note":"1","date":"2016-01-26T00:46:00+01:00","text":"Very great vendor. He is quick on reply and answered many of our questions. Will definately be back and would definately recommend. Product is a great experience as well. Thanks Hood","prod_id":"/listing/1873/"}]},"x":51.94810705931447,"y":-37.67826332049811,"color":"#ffc107","hidden":false,"read_cam0:size":1.1390458882326215,"read_cam0:x":145.94693408227894,"read_cam0:y":13.658266491584952,"renderer1:x":809.4999496993587,"renderer1:y":423.0919682620013,"renderer1:size":0.9234326996706415,"fa2_x":52.0133056640625,"fa2_y":-37.72682571411133},{"id":"2***s","label":"2***s","size":0.1093,"metadata":{"category":"client","transactions":[{"delivery_time":"5 days","note":"1","date":"2016-01-21T00:55:00+01:00","text":"---","prod_id":"/listing/1873/"}]},"x":75.20699679013828,"y":-22.612041945726325,"color":"#ffc107","hidden":false,"read_cam0:size":1.1390458882326215,"read_cam0:x":200.14956930416963,"read_cam0:y":48.76866560348973,"renderer1:x":845.1244235494605,"renderer1:y":446.16814324700533,"renderer1:size":0.9234326996706415,"fa2_x":75.30282592773438,"fa2_y":-22.640323638916016},{"id":"T***p","label":"T***p","size":0.1093,"metadata":{"category":"client","transactions":[{"delivery_time":"Not specified","note":"1","date":"2016-01-17T23:32:00+01:00","text":"Communication is great with this vendor. Finalized early due to positive feedback and bitcoin volatility. I have faith product will arrive. Will update if wrong.","prod_id":"/listing/1873/"}]},"x":80.55927395758277,"y":-30.3907090408954,"color":"#ffc107","hidden":false,"read_cam0:size":1.1390458882326215,"read_cam0:x":212.62254330554615,"read_cam0:y":30.64122014278847,"renderer1:x":853.3222378130295,"renderer1:y":434.2539493311514,"renderer1:size":0.9234326996706415,"fa2_x":80.66106414794922,"fa2_y":-30.429113388061523},{"id":"t***y","label":"t***y","size":0.1093,"metadata":{"category":"client","transactions":[{"delivery_time":"7 days","note":"1","date":"2016-01-07T14:01:00+01:00","text":"---","prod_id":"/listing/1873/"}]},"x":46.14093380622069,"y":-10.056726067760662,"color":"#ffc107","hidden":false,"read_cam0:size":1.1390458882326215,"read_cam0:x":132.41386792346648,"read_cam0:y":78.0276377429514,"renderer1:x":800.6053939362911,"renderer1:y":465.39849032507783,"renderer1:size":0.9234326996706415,"fa2_x":46.198917388916016,"fa2_y":-10.070343971252441},{"id":"w***e","label":"w***e","size":0.1093,"metadata":{"category":"client","transactions":[{"delivery_time":"Not specified","note":"1","date":"2016-01-07T01:09:00+01:00","text":"very honest vendor and ridicuously excellent stealth and fast replies A+++ definitely buying more from him","prod_id":"/listing/1873/"}]},"x":37.44617656972535,"y":-36.54500430800739,"color":"#ffc107","hidden":false,"read_cam0:size":1.1390458882326215,"read_cam0:x":112.15156132642846,"read_cam0:y":16.29921907259101,"renderer1:x":787.2880707368943,"renderer1:y":424.82772420405576,"renderer1:size":0.9234326996706415,"fa2_x":37.493778228759766,"fa2_y":-36.59177017211914},{"id":"h***s","label":"h***s","size":0.18,"metadata":{"category":"client","transactions":[{"delivery_time":"Not specified","note":"1","date":"2015-12-22T19:39:00+01:00","text":"Great vendor! Went above and beyond.","prod_id":"/listing/1873/"},{"delivery_time":"Not specified","note":"1","date":"2015-11-21T20:27:00+01:00","text":"Responsible Human Being","prod_id":"/listing/2286/"}]},"x":22.134291291950724,"y":-13.089013366966268,"color":"#ffc107","hidden":false,"read_cam0:size":1.2289868241708315,"read_cam0:x":76.4686658023668,"read_cam0:y":70.96117995975814,"renderer1:x":763.8356246835064,"renderer1:y":460.7540880837538,"renderer1:size":0.9963484637696587,"fa2_x":22.161659240722656,"fa2_y":-13.104178428649902},{"id":"i***f","label":"i***f","size":1.0092,"metadata":{"category":"client","transactions":[{"delivery_time":"Not specified","note":"1","date":"2015-12-12T06:28:00+01:00","text":"A consummate professional. Safe packaging, quality product. Passionate about his work (for good reason, these are important tools) and it shows!","prod_id":"/listing/1873/"},{"delivery_time":"3 days","note":"1","date":"2015-12-25T04:03:00+01:00","text":"Vendor was able to handle the large quantity like a pro. Excellent quality product, and the vacuum sealing is a welcome bonus.","prod_id":"/listing/2291/"}]},"x":72.16033741876656,"y":15.384978399879241,"color":"#ffc107","hidden":false,"read_cam0:size":2.283852794184462,"read_cam0:x":193.04961877071966,"read_cam0:y":137.31711555732466,"renderer1:x":840.4580083266495,"renderer1:y":504.36627193454666,"renderer1:size":1.8515358978701555,"fa2_x":72.25328826904297,"fa2_y":15.404824256896973},{"id":"r***y","label":"r***y","size":0.1093,"metadata":{"category":"client","transactions":[{"delivery_time":"5 days","note":"1","date":"2015-11-21T10:05:00+01:00","text":"First review so I'll make it detailed for Hood:\n\nProduct was not the same consistency as the stuff I tried and the smell was much more mellow. This stuff is crystally, rolls around easily on paper/etc. \n\nTried 50mg on a dabber wow hit me HARD -- strong fractals, very strong trip zero complaints. \n\nHood had EXCELLENT communication through the whole transaction and weight was a couple mg over and the bonus was included as promised on the listing. Really no issues here, will do business again THANKS HOOD","prod_id":"/listing/1873/"}]},"x":71.64042088413825,"y":-44.54982647035327,"color":"#ffc107","hidden":false,"read_cam0:size":1.1390458882326215,"read_cam0:x":191.83800262745464,"read_cam0:y":-2.355259309785839,"renderer1:x":839.6616782693486,"renderer1:y":412.5671399243475,"renderer1:size":0.9234326996706415,"fa2_x":71.73126220703125,"fa2_y":-44.60606002807617},{"id":"d***s","label":"d***s","size":0.0707,"metadata":{"category":"client","transactions":[{"delivery_time":"Not specified","note":"1","date":"2016-06-26T19:08:00+02:00","text":"---","prod_id":"/listing/2286/"}]},"x":4.075247294912584,"y":7.893529381270255,"color":"#ffc107","hidden":false,"read_cam0:size":1.08994093593821,"read_cam0:x":34.38377759163177,"read_cam0:y":119.85900456671584,"renderer1:x":736.1754935217969,"renderer1:y":492.8919955287762,"renderer1:size":0.8836229614213902,"fa2_x":4.079281330108643,"fa2_y":7.903512954711914},{"id":"b***d","label":"b***d","size":0.1414,"metadata":{"category":"client","transactions":[{"delivery_time":"5 days","note":"1","date":"2016-05-02T06:40:00+02:00","text":"Second time legit in a row. Keep up the work, Hood.","prod_id":"/listing/2286/"},{"delivery_time":"2 days","note":"1","date":"2016-01-20T03:44:00+01:00","text":"Lightning fast shipping. Great packaging.","prod_id":"/listing/2286/"}]},"x":9.138499077245632,"y":-7.123555122652204,"color":"#ffc107","hidden":false,"read_cam0:size":1.17988187187642,"read_cam0:x":46.18320536185258,"read_cam0:y":84.863114269179,"renderer1:x":743.9306221114974,"renderer1:y":469.8910810222776,"renderer1:size":0.9565387255204075,"fa2_x":9.148514747619629,"fa2_y":-7.133455276489258},{"id":"r***i","label":"r***i","size":0.0707,"metadata":{"category":"client","transactions":[{"delivery_time":"5 days","note":"1","date":"2016-04-27T06:26:00+02:00","text":"Had a great experience and great product!  I'm not too experienced, but had any questions answered.  Great experience overall!","prod_id":"/listing/2286/"}]},"x":5.879827354385055,"y":16.227857935118028,"color":"#ffc107","hidden":false,"read_cam0:size":1.08994093593821,"read_cam0:x":38.589180163477565,"read_cam0:y":139.28136632394657,"renderer1:x":738.9394782125147,"renderer1:y":505.65726820777405,"renderer1:size":0.8836229614213902,"fa2_x":5.884376049041748,"fa2_y":16.247814178466797},{"id":"G***g","label":"G***g","size":0.0707,"metadata":{"category":"client","transactions":[{"delivery_time":"5 days","note":"1","date":"2016-04-23T03:54:00+02:00","text":"Trustworthy and professional. Great vendor!","prod_id":"/listing/2286/"}]},"x":-12.805944970317126,"y":13.526593968043954,"color":"#ffc107","hidden":false,"read_cam0:size":1.08994093593821,"read_cam0:x":-4.956238937628411,"read_cam0:y":132.9863270017851,"renderer1:x":710.3194187318538,"renderer1:y":501.5198777875545,"renderer1:size":0.8836229614213902,"fa2_x":-12.82231330871582,"fa2_y":13.542523384094238},{"id":"i***a","label":"i***a","size":0.0707,"metadata":{"category":"client","transactions":[{"delivery_time":"Not specified","note":"1","date":"2016-04-22T17:25:00+02:00","text":"---","prod_id":"/listing/2286/"}]},"x":-1.002606958742436,"y":12.492054126387407,"color":"#ffc107","hidden":false,"read_cam0:size":1.08994093593821,"read_cam0:x":22.55032014778668,"read_cam0:y":130.5754300798435,"renderer1:x":728.3979990597877,"renderer1:y":499.93532504395813,"renderer1:size":0.8836229614213902,"fa2_x":-1.0058132410049438,"fa2_y":12.50683879852295},{"id":"K***0","label":"K***0","size":0.0707,"metadata":{"category":"client","transactions":[{"delivery_time":"Not specified","note":"1","date":"2016-04-19T07:29:00+02:00","text":"---","prod_id":"/listing/2286/"}]},"x":-9.284970637834185,"y":-14.466012126556759,"color":"#ffc107","hidden":false,"read_cam0:size":1.08994093593821,"read_cam0:x":3.249057599647589,"read_cam0:y":67.75221502932268,"renderer1:x":715.7123183709191,"renderer1:y":458.6450082063233,"renderer1:size":0.8836229614213902,"fa2_x":-9.298337936401367,"fa2_y":-14.484466552734375},{"id":"C***z","label":"C***z","size":0.0707,"metadata":{"category":"client","transactions":[{"delivery_time":"4 days","note":"1","date":"2016-04-18T23:41:00+02:00","text":"Delivery speed exceeded expectations, but not as much as the product did. Would highly recommend to anyone in the market for DMT. Between the prices, quality, shipping, stealth, and professionalism of the vendor this is not an opportunity you'll want to pass up","prod_id":"/listing/2286/"}]},"x":-12.424720595011431,"y":-5.863819013072082,"color":"#ffc107","hidden":false,"read_cam0:size":1.08994093593821,"read_cam0:x":-4.06783170961685,"read_cam0:y":87.79880972212771,"renderer1:x":710.9033209707943,"renderer1:y":471.82055558504203,"renderer1:size":0.8836229614213902,"fa2_x":-12.442289352416992,"fa2_y":-5.8709259033203125},{"id":"C***e","label":"C***e","size":0.0707,"metadata":{"category":"client","transactions":[{"delivery_time":"3 days","note":"1","date":"2016-04-02T05:06:00+02:00","text":"super legit, good communication, nice delivery","prod_id":"/listing/2286/"}]},"x":2.952659284393912,"y":-11.033911914500237,"color":"#ffc107","hidden":false,"read_cam0:size":1.08994093593821,"read_cam0:x":31.767692768031015,"read_cam0:y":75.75039886320272,"renderer1:x":734.4560818177996,"renderer1:y":463.90178381643784,"renderer1:size":0.8836229614213902,"fa2_x":2.9547371864318848,"fa2_y":-11.048158645629883},{"id":"b***m","label":"b***m","size":0.0707,"metadata":{"category":"client","transactions":[{"delivery_time":"7 days","note":"1","date":"2016-03-01T16:35:00+01:00","text":"Product is most definitely legit! Thanks!","prod_id":"/listing/2286/"}]},"x":-15.158286721875935,"y":-0.7686395177015021,"color":"#ffc107","hidden":false,"read_cam0:size":1.08994093593821,"read_cam0:x":-10.43814814965723,"read_cam0:y":99.67264199760524,"renderer1:x":706.7164549539287,"renderer1:y":479.62458625009367,"renderer1:size":0.8836229614213902,"fa2_x":-15.178038597106934,"fa2_y":-0.770764946937561},{"id":"g***g","label":"g***g","size":0.0707,"metadata":{"category":"client","transactions":[{"delivery_time":"12 days","note":"1","date":"2016-02-18T21:54:00+01:00","text":"Delivery took a strangely long time, but that was USPS, not Hood. Hood reached out and is clearly a vendor who cares. Haven't sampled the goods yet. Can't hardly wait - Thanks, Hood!","prod_id":"/listing/2286/"}]},"x":-8.534297929246659,"y":8.709097283277304,"color":"#ffc107","hidden":false,"read_cam0:size":1.08994093593821,"read_cam0:x":4.998429107294235,"read_cam0:y":121.75960816399704,"renderer1:x":716.8620860763664,"renderer1:y":494.14115994437293,"renderer1:size":0.8836229614213902,"fa2_x":-8.546135902404785,"fa2_y":8.717498779296875},{"id":"p***s","label":"p***s","size":0.0707,"metadata":{"category":"client","transactions":[{"delivery_time":"6 days","note":"1","date":"2016-02-14T22:58:00+01:00","text":"Great order. Exactly as described! Shipped next day. 6 days to East Coast.","prod_id":"/listing/2286/"}]},"x":11.223480832427905,"y":9.199872709109234,"color":"#ffc107","hidden":false,"read_cam0:size":1.08994093593821,"read_cam0:x":51.04205747510172,"read_cam0:y":122.9033137187374,"renderer1:x":747.1240840039194,"renderer1:y":494.89285602815687,"renderer1:size":0.8836229614213902,"fa2_x":11.236518859863281,"fa2_y":9.210982322692871},{"id":"v***k","label":"v***k","size":0.0707,"metadata":{"category":"client","transactions":[{"delivery_time":"Not specified","note":"1","date":"2016-02-12T03:16:00+01:00","text":"Fantastic Product, Great Stealth!","prod_id":"/listing/2286/"}]},"x":11.622796248645392,"y":1.8204963607662141,"color":"#ffc107","hidden":false,"read_cam0:size":1.08994093593821,"read_cam0:x":51.972624157097314,"read_cam0:y":105.70637745035613,"renderer1:x":747.7356953820898,"renderer1:y":483.59023570560475,"renderer1:size":0.8836229614213902,"fa2_x":11.635960578918457,"fa2_y":1.8221758604049683},{"id":"K***a","label":"K***a","size":0.0707,"metadata":{"category":"client","transactions":[{"delivery_time":"3 days","note":"1","date":"2016-01-30T05:48:00+01:00","text":"Superfast and responsive!","prod_id":"/listing/2286/"}]},"x":-6.017486168527437,"y":-8.262467759299469,"color":"#ffc107","hidden":false,"read_cam0:size":1.08994093593821,"read_cam0:x":10.863620067275479,"read_cam0:y":82.20898645361164,"renderer1:x":720.7169603112508,"renderer1:y":468.14666570790337,"renderer1:size":0.8836229614213902,"fa2_x":-6.02738618850708,"fa2_y":-8.273707389831543},{"id":"f***w","label":"f***w","size":0.0707,"metadata":{"category":"client","transactions":[{"delivery_time":"Not specified","note":"1","date":"2016-01-02T21:25:00+01:00","text":"---","prod_id":"/listing/2286/"}]},"x":-1.4185673227836744,"y":-15.93129313715016,"color":"#ffc107","hidden":false,"read_cam0:size":1.08994093593821,"read_cam0:x":21.580963994512828,"read_cam0:y":64.33751669101363,"renderer1:x":727.7608934505794,"renderer1:y":456.4007108366274,"renderer1:size":0.8836229614213902,"fa2_x":-1.4230479001998901,"fa2_y":-15.953200340270996},{"id":"c***3","label":"c***3","size":0.0707,"metadata":{"category":"client","transactions":[{"delivery_time":"4 days","note":"1","date":"2015-11-21T19:24:00+01:00","text":"Great vendor and great product will be using again","prod_id":"/listing/2286/"}]},"x":-4.210260387930497,"y":18.546790360884746,"color":"#ffc107","hidden":false,"read_cam0:size":1.08994093593821,"read_cam0:x":15.075188241119822,"read_cam0:y":144.68541827280094,"renderer1:x":723.484997320205,"renderer1:y":509.20906059846584,"renderer1:size":0.8836229614213902,"fa2_x":-4.2166852951049805,"fa2_y":18.56931495666504},{"id":"b***s","label":"b***s","size":0.0707,"metadata":{"category":"client","transactions":[{"delivery_time":"3 days","note":"1","date":"2015-11-21T17:23:00+01:00","text":"5/5 Excellent! Perfect order with Fast delivery. You can feel good about hood!","prod_id":"/listing/2286/"}]},"x":-15.51017842590424,"y":6.314554614935157,"color":"#ffc107","hidden":false,"read_cam0:size":1.08994093593821,"read_cam0:x":-11.258198370961587,"read_cam0:y":116.17935372032093,"renderer1:x":706.1774800951413,"renderer1:y":490.47355914061404,"renderer1:size":0.8836229614213902,"fa2_x":-15.530227661132812,"fa2_y":6.321224212646484},{"id":"F***m","label":"F***m","size":0.0321,"metadata":{"category":"client","transactions":[{"delivery_time":"Not specified","note":"1","date":"2016-06-12T23:54:00+02:00","text":"---","prod_id":"/listing/2287/"}]},"x":102.70147801111236,"y":74.17004873397862,"color":"#ffc107","hidden":false,"read_cam0:size":1.0408359836437984,"read_cam0:x":264.22284853127735,"read_cam0:y":274.31014319912686,"renderer1:x":887.2363402666485,"renderer1:y":594.4044132701672,"renderer1:size":0.8438132231721389,"fa2_x":102.83335876464844,"fa2_y":74.26588439941406},{"id":"X***g","label":"X***g","size":0.0321,"metadata":{"category":"client","transactions":[{"delivery_time":"Not specified","note":"1","date":"2016-06-11T03:19:00+02:00","text":"Very Stealth. Good dealer. Will buy again.","prod_id":"/listing/2287/"}]},"x":96.36789516715892,"y":88.11731902171931,"color":"#ffc107","hidden":false,"read_cam0:size":1.0408359836437984,"read_cam0:x":249.46303477785125,"read_cam0:y":306.81293299247045,"renderer1:x":877.5355093579892,"renderer1:y":615.7667470443134,"renderer1:size":0.8438132231721389,"fa2_x":96.49114227294922,"fa2_y":88.23005676269531},{"id":"d***r","label":"d***r","size":0.0321,"metadata":{"category":"client","transactions":[{"delivery_time":"Not specified","note":"1","date":"2016-04-06T13:32:00+02:00","text":"great product, shipping was fast.  exactly what I wanted.  great vendor.","prod_id":"/listing/2287/"}]},"x":106.10365344145168,"y":88.71146373605283,"color":"#ffc107","hidden":false,"read_cam0:size":1.0408359836437984,"read_cam0:x":272.15129550126215,"read_cam0:y":308.1975308641976,"renderer1:x":892.447281590772,"renderer1:y":616.67676867836,"renderer1:size":0.8438132231721389,"fa2_x":106.23868560791016,"fa2_y":88.82551574707031},{"id":"k***2","label":"k***2","size":0.0321,"metadata":{"category":"client","transactions":[{"delivery_time":"3 days","note":"1","date":"2016-01-21T05:57:00+01:00","text":"arrived on time.","prod_id":"/listing/2287/"}]},"x":110.25459737852553,"y":80.39986285735189,"color":"#ffc107","hidden":false,"read_cam0:size":1.0408359836437984,"read_cam0:x":281.8246764171862,"read_cam0:y":288.8281337970136,"renderer1:x":898.8050740499518,"renderer1:y":603.9463068384998,"renderer1:size":0.8438132231721389,"fa2_x":110.3952407836914,"fa2_y":80.50420379638672},{"id":"t***s","label":"t***s","size":0.3214,"metadata":{"category":"client","transactions":[{"delivery_time":"Not specified","note":"1","date":"2016-02-24T19:14:00+01:00","text":"---","prod_id":"/listing/2290/"}]},"x":31.85524678457366,"y":64.66076747974455,"color":"#ffc107","hidden":false,"read_cam0:size":1.4088686960472514,"read_cam0:x":99.12243004789742,"read_cam0:y":252.14966567802915,"renderer1:x":778.7247242386761,"renderer1:y":579.8395245203064,"renderer1:size":1.1421799919676934,"fa2_x":31.896074295043945,"fa2_y":64.74264526367188},{"id":"r***s","label":"r***s","size":0.3214,"metadata":{"category":"client","transactions":[{"delivery_time":"Not specified","note":"1","date":"2015-12-06T14:17:00+01:00","text":"Perfect transaction all around - thank you Hood!","prod_id":"/listing/2290/"}]},"x":26.65090730152817,"y":58.61888516761561,"color":"#ffc107","hidden":false,"read_cam0:size":1.4088686960472514,"read_cam0:x":86.99421078055381,"read_cam0:y":238.069632331299,"renderer1:x":770.7534987001198,"renderer1:y":570.5854766734487,"renderer1:size":1.1421799919676934,"fa2_x":26.685487747192383,"fa2_y":58.6921272277832},{"id":"p***5","label":"p***5","size":0.0242,"metadata":{"category":"client","transactions":[{"delivery_time":"7 days","note":"1","date":"2015-12-10T22:28:00+01:00","text":"First time that I smoked DMT and it was amazing! This product is absolutely awesome! VERY GOOD! I will buy again","prod_id":"/listing/2647/"}]},"x":-41.83943016582468,"y":-174.66412160527935,"color":"#ffc107","hidden":false,"read_cam0:size":1.030786006360745,"read_cam0:x":-72.61602087411214,"read_cam0:y":-305.57427612319196,"renderer1:x":665.8502868818509,"renderer1:y":213.2776055483468,"renderer1:size":0.8356656342558413,"fa2_x":-41.892974853515625,"fa2_y":-174.8919677734375},{"id":"S***h","label":"S***h","size":0.019,"metadata":{"category":"client","transactions":[{"delivery_time":"2 days","note":"1","date":"2016-09-14T13:11:00+02:00","text":"Unbelievably well done. Postage was super good too. Highly recommended. This was my first time and am impressed. Haven't product as of yet.","prod_id":"/listing/2665/"}]},"x":-101.13508368280462,"y":19.996279255105648,"color":"#ffc107","hidden":false,"read_cam0:size":1.0241708314402544,"read_cam0:x":-210.7989141686773,"read_cam0:y":148.06331458259416,"renderer1:x":575.0301109152856,"renderer1:y":511.42916997624724,"renderer1:size":0.8303026643362531,"fa2_x":-101.26746368408203,"fa2_y":20.021366119384766},{"id":"S***1","label":"S***1","size":0.102,"metadata":{"category":"client","transactions":[{"delivery_time":"Next Day","note":"1","date":"2016-08-18T11:13:00+02:00","text":"legit and fast shipping a++","prod_id":"/listing/2665/"},{"delivery_time":"Next Day","note":"1","date":"2016-08-18T11:10:00+02:00","text":"legit and fast shipping a++","prod_id":"/listing/2665/"},{"delivery_time":"Same Day","note":"1","date":"2016-08-11T09:48:00+02:00","text":"fast cool stealthy shipping heaviest dmt trip i never broke threw this heavy injecting it lol I'll ordor again saturday thanks for the next level experience????","prod_id":"/listing/2665/"},{"delivery_time":"Not specified","note":"1","date":"2016-08-08T09:53:00+02:00","text":"legit fast stealthy shipping will be a returning customer","prod_id":"/listing/9351/"}]},"x":-84.69430065470121,"y":-2.828963066467161,"color":"#ffc107","hidden":false,"read_cam0:size":1.129759200363471,"read_cam0:x":-172.48522957118905,"read_cam0:y":94.87125349431743,"renderer1:x":600.2116329844014,"renderer1:y":476.4688920946465,"renderer1:size":0.9159039149758348,"fa2_x":-84.80421447753906,"fa2_y":-2.8326187133789062},{"id":"V***s","label":"V***s","size":0.0571,"metadata":{"category":"client","transactions":[{"delivery_time":"Next Day","note":"1","date":"2016-08-10T10:59:00+02:00","text":"Good service! Would recommend! 100mg is smaller than I thought though!","prod_id":"/listing/2665/"},{"delivery_time":"2 days","note":"1","date":"2016-08-18T03:41:00+02:00","text":"---","prod_id":"/listing/2666/"}]},"x":-90.49387913728629,"y":42.74251193356141,"color":"#ffc107","hidden":false,"read_cam0:size":1.0726397092230804,"read_cam0:x":-186.00059683808357,"read_cam0:y":201.071251195694,"renderer1:x":591.3287097500795,"renderer1:y":546.2684327536147,"renderer1:size":0.8695967324009286,"fa2_x":-90.6109390258789,"fa2_y":42.79723358154297},{"id":"e***h","label":"e***h","size":0.019,"metadata":{"category":"client","transactions":[{"delivery_time":"Not specified","note":"1","date":"2016-05-21T15:28:00+02:00","text":"---","prod_id":"/listing/2665/"}]},"x":-110.27102849398857,"y":16.787687634130066,"color":"#ffc107","hidden":false,"read_cam0:size":1.0241708314402544,"read_cam0:x":-232.0893665393111,"read_cam0:y":140.58599630900198,"renderer1:x":561.0370428544883,"renderer1:y":506.514731255399,"renderer1:size":0.8303026643362531,"fa2_x":-110.41468048095703,"fa2_y":16.81037139892578},{"id":"a***d","label":"a***d","size":0.019,"metadata":{"category":"client","transactions":[{"delivery_time":"Next Day","note":"1","date":"2016-05-14T05:31:00+02:00","text":"Top marks in every category, could not ask for better","prod_id":"/listing/2665/"}]},"x":-116.66845762171079,"y":22.888182964119768,"color":"#ffc107","hidden":false,"read_cam0:size":1.0241708314402544,"read_cam0:x":-246.9979679979734,"read_cam0:y":154.80262173141278,"renderer1:x":551.2384217979385,"renderer1:y":515.8585537194556,"renderer1:size":0.8303026643362531,"fa2_x":-116.82008361816406,"fa2_y":22.91944122314453},{"id":"s***r","label":"s***r","size":0.0761,"metadata":{"category":"client","transactions":[{"delivery_time":"2 days","note":"1","date":"2016-01-06T07:07:00+01:00","text":"Prompt response from vendor, very discreet packaging, free express shipping with tracking! Only need a little bit of this stuff to get all tingly :) Thank you, would buy again","prod_id":"/listing/2665/"},{"delivery_time":"2 days","note":"1","date":"2016-03-03T15:21:00+01:00","text":"Good stuff, great communication, thank you once again :-)","prod_id":"/listing/2667/"}]},"x":-119.85451061976225,"y":50.40369500058545,"color":"#ffc107","hidden":false,"read_cam0:size":1.0968105406633348,"read_cam0:x":-254.42276214978259,"read_cam0:y":218.9249112781747,"renderer1:x":546.3585043544284,"renderer1:y":558.0026822810264,"renderer1:size":0.8891921994148088,"fa2_x":-120.0096435546875,"fa2_y":50.47358322143555},{"id":"a***e","label":"a***e","size":0.0381,"metadata":{"category":"client","transactions":[{"delivery_time":"Next Day","note":"1","date":"2016-11-01T16:49:00+01:00","text":"Arrived on time, as ordered.  Thanks.","prod_id":"/listing/2666/"}]},"x":-75.20749827367598,"y":59.37213779436223,"color":"#ffc107","hidden":false,"read_cam0:size":1.048468877782826,"read_cam0:x":-150.3771369308332,"read_cam0:y":239.8250160933782,"renderer1:x":614.7420919725635,"renderer1:y":571.7391959100336,"renderer1:size":0.8500012653870483,"fa2_x":-75.30391693115234,"fa2_y":59.44847869873047},{"id":"b***i","label":"b***i","size":0.0952,"metadata":{"category":"client","transactions":[{"delivery_time":"2 days","note":"1","date":"2016-11-17T02:26:00+01:00","text":"Order arrived on time","prod_id":"/listing/2668/"}]},"x":-39.83384822043823,"y":76.74396436423137,"color":"#ffc107","hidden":false,"read_cam0:size":1.1211085870059065,"read_cam0:x":-67.94220248245749,"read_cam0:y":280.30840930783216,"renderer1:x":668.9221360713232,"renderer1:y":598.346750635514,"renderer1:size":0.9088908004656042,"fa2_x":-39.8845100402832,"fa2_y":76.84246063232422},{"id":"n***e","label":"n***e","size":0.0952,"metadata":{"category":"client","transactions":[{"delivery_time":"Not specified","note":"1","date":"2016-01-05T12:33:00+01:00","text":"Quick, great stealth, looks lovely, thank you!","prod_id":"/listing/2668/"}]},"x":-32.83462926654663,"y":71.68621237576909,"color":"#ffc107","hidden":false,"read_cam0:size":1.1211085870059065,"read_cam0:x":-51.63118694446462,"read_cam0:y":268.5217982852903,"renderer1:x":679.6424883959489,"renderer1:y":590.6000458040064,"renderer1:size":0.9088908004656042,"fa2_x":-32.877044677734375,"fa2_y":71.77735137939453},{"id":"a***r","label":"a***r","size":0.4379,"metadata":{"category":"client","transactions":[{"delivery_time":"Not specified","note":"1","date":"2016-01-16T04:08:00+01:00","text":"---","prod_id":"/listing/2667/"},{"delivery_time":"2 days","note":"1","date":"2016-08-10T11:23:00+02:00","text":"As always, great stealth, quick delivery, top quality. A+","prod_id":"/listing/2670/"},{"delivery_time":"Next Day","note":"1","date":"2016-04-18T04:15:00+02:00","text":"Quick, stealth, love your work","prod_id":"/listing/2670/"}]},"x":-117.20360998709563,"y":82.0511346210863,"color":"#ffc107","hidden":false,"read_cam0:size":1.5570740572467061,"read_cam0:x":-248.24508979891843,"read_cam0:y":292.6762659347782,"renderer1:x":550.4187557834766,"renderer1:y":606.4754769084112,"renderer1:size":1.2623311449738532,"fa2_x":-117.35289764404297,"fa2_y":82.16303253173828},{"id":"L***r","label":"L***r","size":0.0424,"metadata":{"category":"client","transactions":[{"delivery_time":"Not specified","note":"1","date":"2016-08-18T18:01:00+02:00","text":"Order arrived quickly and overall very positive experience with vendor.","prod_id":"/listing/3421/"}]},"x":-11.337974983752982,"y":-109.98420307170883,"color":"#ffc107","hidden":false,"read_cam0:size":1.0539391185824625,"read_cam0:x":-1.5352741960065053,"read_cam0:y":-154.84386418049965,"renderer1:x":712.5678346710628,"renderer1:y":312.34458996129086,"renderer1:size":0.8544360289744002,"fa2_x":-11.352649688720703,"fa2_y":-110.12960815429688},{"id":"R***N","label":"R***N","size":0.0424,"metadata":{"category":"client","transactions":[{"delivery_time":"Not specified","note":"1","date":"2016-05-04T04:53:00+02:00","text":"Received item today! Looks legit. Eagerly awaiting the right time to dive in :)","prod_id":"/listing/3421/"}]},"x":-12.173205558312509,"y":-123.24093554494732,"color":"#ffc107","hidden":false,"read_cam0:size":1.0539391185824625,"read_cam0:x":-3.4816997856606804,"read_cam0:y":-185.7374211299907,"renderer1:x":711.288553926945,"renderer1:y":292.039918293975,"renderer1:size":0.8544360289744002,"fa2_x":-12.189348220825195,"fa2_y":-123.40247344970703},{"id":"l***6","label":"l***6","size":0.0424,"metadata":{"category":"client","transactions":[{"delivery_time":"Same Day","note":"1","date":"2016-04-28T10:39:00+02:00","text":"Fast delivery.","prod_id":"/listing/3421/"}]},"x":-5.95265055100215,"y":-116.64574346680828,"color":"#ffc107","hidden":false,"read_cam0:size":1.0539391185824625,"read_cam0:x":11.01471332094235,"read_cam0:y":-170.36795188331692,"renderer1:x":720.8162657719936,"renderer1:y":302.1414429343664,"renderer1:size":0.8544360289744002,"fa2_x":-5.961992263793945,"fa2_y":-116.79853820800781},{"id":"N***2","label":"N***2","size":0.1028,"metadata":{"category":"client","transactions":[{"delivery_time":"Next Day","note":"1","date":"2016-04-01T01:14:00+02:00","text":"Great Product!","prod_id":"/listing/3424/"}]},"x":-45.258145331682464,"y":-91.8062587195832,"color":"#ffc107","hidden":false,"read_cam0:size":1.1307769195820083,"read_cam0:x":-80.58301212808253,"read_cam0:y":-112.48188997601575,"renderer1:x":660.614012475096,"renderer1:y":340.1868348283235,"renderer1:size":0.9167289872711563,"fa2_x":-45.31827926635742,"fa2_y":-91.93531036376953},{"id":"J***1","label":"J***1","size":0.1157,"metadata":{"category":"client","transactions":[{"delivery_time":"3 days","note":"1","date":"2016-08-31T22:10:00+02:00","text":"Came sooner than expected and everything is what it should be. Can't wait to try it all. Awesome vendor will order from again.","prod_id":"/listing/3430/"}]},"x":-59.4996853194874,"y":-114.16573791191732,"color":"#ffc107","hidden":false,"read_cam0:size":1.1471876419809177,"read_cam0:x":-113.77156953088763,"read_cam0:y":-164.58853429306652,"renderer1:x":638.8009605731226,"renderer1:y":305.939942951383,"renderer1:size":0.9300332780332116,"fa2_x":-59.57593536376953,"fa2_y":-114.31822204589844},{"id":"F***d","label":"F***d","size":0.0707,"metadata":{"category":"client","transactions":[{"delivery_time":"Not specified","note":"1","date":"2016-03-24T15:00:00+01:00","text":"---","prod_id":"/listing/8371/"}]},"x":-126.44249242176356,"y":-79.66269710895584,"color":"#ffc107","hidden":false,"read_cam0:size":1.08994093593821,"read_cam0:x":-269.775428532181,"read_cam0:y":-84.18247208062523,"renderer1:x":536.2680233320555,"renderer1:y":358.78651856436977,"renderer1:size":0.8836229614213902,"fa2_x":-126.61074829101562,"fa2_y":-79.76882934570312},{"id":"O***l","label":"O***l","size":0.19279999999999997,"metadata":{"category":"client","transactions":[{"delivery_time":"Not specified","note":"1","date":"2016-10-10T12:16:00+02:00","text":"---","prod_id":"/listing/9350/"},{"delivery_time":"Not specified","note":"1","date":"2016-09-22T06:44:00+02:00","text":"As Rx'd. Excellent vendor!!!","prod_id":"/listing/9351/"}]},"x":-51.28908370681043,"y":-24.756673518269675,"color":"#ffc107","hidden":false,"read_cam0:size":1.2452703316674238,"read_cam0:x":-94.6375416682243,"read_cam0:y":43.77080525171792,"renderer1:x":651.3767269071785,"renderer1:y":442.8833187236351,"renderer1:size":1.009549620494799,"fa2_x":-51.35629653930664,"fa2_y":-24.790035247802734},{"id":"C***5","label":"C***5","size":0.045,"metadata":{"category":"client","transactions":[{"delivery_time":"Not specified","note":"1","date":"2016-10-19T10:11:00+02:00","text":"---","prod_id":"/listing/9351/"}]},"x":-71.53460329215969,"y":-30.518626992993408,"color":"#ffc107","hidden":false,"read_cam0:size":1.057246706042708,"read_cam0:x":-141.81780373843196,"read_cam0:y":30.34311949498708,"renderer1:x":620.3676808436347,"renderer1:y":434.05802382515293,"renderer1:size":0.8571175139341944,"fa2_x":-71.62622833251953,"fa2_y":-30.55728530883789},{"id":"m***t","label":"m***t","size":0.045,"metadata":{"category":"client","transactions":[{"delivery_time":"3 days","note":"1","date":"2016-05-30T04:30:00+02:00","text":"---","prod_id":"/listing/9351/"}]},"x":-63.24762618049826,"y":-32.75485993555025,"color":"#ffc107","hidden":false,"read_cam0:size":1.057246706042708,"read_cam0:x":-122.50579002350938,"read_cam0:y":25.13179084347579,"renderer1:x":633.0604276955852,"renderer1:y":430.63289808154195,"renderer1:size":0.8571175139341944,"fa2_x":-63.328826904296875,"fa2_y":-32.79705047607422},{"id":"m***f","label":"m***f","size":0.1607,"metadata":{"category":"client","transactions":[{"delivery_time":"5 days","note":"1","date":"2016-03-12T23:48:00+01:00","text":"Wow!!  That doesn't even cover it.  Be careful oh my brothers and sisters because this is the genuine article like I've never experienced before. This vendor ain't messin' around.  You'd better be ready for a ride.","prod_id":"/listing/9753/"}]},"x":58.52202838557971,"y":79.9157127420397,"color":"#ffc107","hidden":false,"read_cam0:size":1.2044343480236257,"read_cam0:x":161.26683386033005,"read_cam0:y":287.6998678996898,"renderer1:x":819.568894996855,"renderer1:y":603.2047584102614,"renderer1:size":0.9764435946450332,"fa2_x":58.5963020324707,"fa2_y":80.0172348022461}],"edges":[{"id":1,"source":"vendor-0","target":"/listing/1873/","weight":1,"color":"#37474f","hidden":false,"read_cam0:size":null,"renderer1:size":0},{"id":2,"source":"vendor-0","target":"/listing/2286/","weight":1,"color":"#37474f","hidden":false,"read_cam0:size":null,"renderer1:size":0},{"id":3,"source":"vendor-0","target":"/listing/2287/","weight":1,"color":"#37474f","hidden":false,"read_cam0:size":null,"renderer1:size":0},{"id":4,"source":"vendor-0","target":"/listing/2290/","weight":1,"color":"#37474f","hidden":false,"read_cam0:size":null,"renderer1:size":0},{"id":5,"source":"vendor-0","target":"/listing/2291/","weight":1,"color":"#37474f","hidden":false,"read_cam0:size":null,"renderer1:size":0},{"id":6,"source":"vendor-1","target":"/listing/2647/","weight":1,"color":"#37474f","hidden":false,"read_cam0:size":null,"renderer1:size":0},{"id":7,"source":"vendor-2","target":"/listing/2665/","weight":1,"color":"#37474f","hidden":false,"read_cam0:size":null,"renderer1:size":0},{"id":8,"source":"vendor-2","target":"/listing/2666/","weight":1,"color":"#37474f","hidden":false,"read_cam0:size":null,"renderer1:size":0},{"id":9,"source":"vendor-2","target":"/listing/2667/","weight":1,"color":"#37474f","hidden":false,"read_cam0:size":null,"renderer1:size":0},{"id":10,"source":"vendor-2","target":"/listing/2668/","weight":1,"color":"#37474f","hidden":false,"read_cam0:size":null,"renderer1:size":0},{"id":11,"source":"vendor-2","target":"/listing/2670/","weight":1,"color":"#37474f","hidden":false,"read_cam0:size":null,"renderer1:size":0},{"id":12,"source":"vendor-3","target":"/listing/3421/","weight":1,"color":"#37474f","hidden":false,"read_cam0:size":null,"renderer1:size":0},{"id":13,"source":"vendor-3","target":"/listing/3424/","weight":1,"color":"#37474f","hidden":false,"read_cam0:size":null,"renderer1:size":0},{"id":14,"source":"vendor-3","target":"/listing/3430/","weight":1,"color":"#37474f","hidden":false,"read_cam0:size":null,"renderer1:size":0},{"id":15,"source":"vendor-4","target":"/listing/8371/","weight":1,"color":"#37474f","hidden":false,"read_cam0:size":null,"renderer1:size":0},{"id":16,"source":"vendor-5","target":"/listing/9350/","weight":1,"color":"#37474f","hidden":false,"read_cam0:size":null,"renderer1:size":0},{"id":17,"source":"vendor-5","target":"/listing/9351/","weight":1,"color":"#37474f","hidden":false,"read_cam0:size":null,"renderer1:size":0},{"id":18,"source":"vendor-0","target":"/listing/9753/","weight":1,"color":"#37474f","hidden":false,"read_cam0:size":null,"renderer1:size":0},{"id":19,"source":"P***g","target":"/listing/1873/","weight":1,"color":"#37474f","hidden":false,"read_cam0:size":null,"renderer1:size":0},{"id":20,"source":"s***w","target":"/listing/1873/","weight":1,"color":"#37474f","hidden":false,"read_cam0:size":null,"renderer1:size":0},{"id":21,"source":"r***e","target":"/listing/1873/","weight":2,"color":"#37474f","hidden":false,"read_cam0:size":null,"renderer1:size":0},{"id":22,"source":"s***e","target":"/listing/1873/","weight":1,"color":"#37474f","hidden":false,"read_cam0:size":null,"renderer1:size":0},{"id":23,"source":"d***3","target":"/listing/1873/","weight":1,"color":"#37474f","hidden":false,"read_cam0:size":null,"renderer1:size":0},{"id":24,"source":"m***e","target":"/listing/1873/","weight":1,"color":"#37474f","hidden":false,"read_cam0:size":null,"renderer1:size":0},{"id":25,"source":"W***o","target":"/listing/1873/","weight":1,"color":"#37474f","hidden":false,"read_cam0:size":null,"renderer1:size":0},{"id":26,"source":"w***u","target":"/listing/1873/","weight":1,"color":"#37474f","hidden":false,"read_cam0:size":null,"renderer1:size":0},{"id":27,"source":"G***5","target":"/listing/1873/","weight":1,"color":"#37474f","hidden":false,"read_cam0:size":null,"renderer1:size":0},{"id":28,"source":"A***1","target":"/listing/1873/","weight":1,"color":"#37474f","hidden":false,"read_cam0:size":null,"renderer1:size":0},{"id":29,"source":"H***7","target":"/listing/1873/","weight":1,"color":"#37474f","hidden":false,"read_cam0:size":null,"renderer1:size":0},{"id":30,"source":"2***s","target":"/listing/1873/","weight":1,"color":"#37474f","hidden":false,"read_cam0:size":null,"renderer1:size":0},{"id":31,"source":"T***p","target":"/listing/1873/","weight":1,"color":"#37474f","hidden":false,"read_cam0:size":null,"renderer1:size":0},{"id":32,"source":"t***y","target":"/listing/1873/","weight":1,"color":"#37474f","hidden":false,"read_cam0:size":null,"renderer1:size":0},{"id":33,"source":"w***e","target":"/listing/1873/","weight":1,"color":"#37474f","hidden":false,"read_cam0:size":null,"renderer1:size":0},{"id":34,"source":"h***s","target":"/listing/1873/","weight":1,"color":"#37474f","hidden":false,"read_cam0:size":null,"renderer1:size":0},{"id":35,"source":"i***f","target":"/listing/1873/","weight":1,"color":"#37474f","hidden":false,"read_cam0:size":null,"renderer1:size":0},{"id":36,"source":"r***y","target":"/listing/1873/","weight":1,"color":"#37474f","hidden":false,"read_cam0:size":null,"renderer1:size":0},{"id":37,"source":"d***s","target":"/listing/2286/","weight":1,"color":"#37474f","hidden":false,"read_cam0:size":null,"renderer1:size":0},{"id":38,"source":"b***d","target":"/listing/2286/","weight":2,"color":"#37474f","hidden":false,"read_cam0:size":null,"renderer1:size":0},{"id":39,"source":"r***i","target":"/listing/2286/","weight":1,"color":"#37474f","hidden":false,"read_cam0:size":null,"renderer1:size":0},{"id":40,"source":"G***g","target":"/listing/2286/","weight":1,"color":"#37474f","hidden":false,"read_cam0:size":null,"renderer1:size":0},{"id":41,"source":"i***a","target":"/listing/2286/","weight":1,"color":"#37474f","hidden":false,"read_cam0:size":null,"renderer1:size":0},{"id":42,"source":"K***0","target":"/listing/2286/","weight":1,"color":"#37474f","hidden":false,"read_cam0:size":null,"renderer1:size":0},{"id":43,"source":"C***z","target":"/listing/2286/","weight":1,"color":"#37474f","hidden":false,"read_cam0:size":null,"renderer1:size":0},{"id":44,"source":"C***e","target":"/listing/2286/","weight":1,"color":"#37474f","hidden":false,"read_cam0:size":null,"renderer1:size":0},{"id":45,"source":"b***m","target":"/listing/2286/","weight":1,"color":"#37474f","hidden":false,"read_cam0:size":null,"renderer1:size":0},{"id":46,"source":"g***g","target":"/listing/2286/","weight":1,"color":"#37474f","hidden":false,"read_cam0:size":null,"renderer1:size":0},{"id":47,"source":"p***s","target":"/listing/2286/","weight":1,"color":"#37474f","hidden":false,"read_cam0:size":null,"renderer1:size":0},{"id":48,"source":"v***k","target":"/listing/2286/","weight":1,"color":"#37474f","hidden":false,"read_cam0:size":null,"renderer1:size":0},{"id":49,"source":"K***a","target":"/listing/2286/","weight":1,"color":"#37474f","hidden":false,"read_cam0:size":null,"renderer1:size":0},{"id":50,"source":"f***w","target":"/listing/2286/","weight":1,"color":"#37474f","hidden":false,"read_cam0:size":null,"renderer1:size":0},{"id":51,"source":"h***s","target":"/listing/2286/","weight":1,"color":"#37474f","hidden":false,"read_cam0:size":null,"renderer1:size":0},{"id":52,"source":"c***3","target":"/listing/2286/","weight":1,"color":"#37474f","hidden":false,"read_cam0:size":null,"renderer1:size":0},{"id":53,"source":"b***s","target":"/listing/2286/","weight":1,"color":"#37474f","hidden":false,"read_cam0:size":null,"renderer1:size":0},{"id":54,"source":"F***m","target":"/listing/2287/","weight":1,"color":"#37474f","hidden":false,"read_cam0:size":null,"renderer1:size":0},{"id":55,"source":"X***g","target":"/listing/2287/","weight":1,"color":"#37474f","hidden":false,"read_cam0:size":null,"renderer1:size":0},{"id":56,"source":"d***r","target":"/listing/2287/","weight":1,"color":"#37474f","hidden":false,"read_cam0:size":null,"renderer1:size":0},{"id":57,"source":"k***2","target":"/listing/2287/","weight":1,"color":"#37474f","hidden":false,"read_cam0:size":null,"renderer1:size":0},{"id":58,"source":"i***f","target":"/listing/2291/","weight":1,"color":"#37474f","hidden":false,"read_cam0:size":null,"renderer1:size":0},{"id":59,"source":"A***1","target":"/listing/2290/","weight":1,"color":"#37474f","hidden":false,"read_cam0:size":null,"renderer1:size":0},{"id":60,"source":"t***s","target":"/listing/2290/","weight":1,"color":"#37474f","hidden":false,"read_cam0:size":null,"renderer1:size":0},{"id":61,"source":"r***s","target":"/listing/2290/","weight":1,"color":"#37474f","hidden":false,"read_cam0:size":null,"renderer1:size":0},{"id":62,"source":"p***5","target":"/listing/2647/","weight":1,"color":"#37474f","hidden":false,"read_cam0:size":null,"renderer1:size":0},{"id":63,"source":"S***h","target":"/listing/2665/","weight":1,"color":"#37474f","hidden":false,"read_cam0:size":null,"renderer1:size":0},{"id":64,"source":"S***1","target":"/listing/2665/","weight":3,"color":"#37474f","hidden":false,"read_cam0:size":null,"renderer1:size":0},{"id":65,"source":"V***s","target":"/listing/2665/","weight":1,"color":"#37474f","hidden":false,"read_cam0:size":null,"renderer1:size":0},{"id":66,"source":"e***h","target":"/listing/2665/","weight":1,"color":"#37474f","hidden":false,"read_cam0:size":null,"renderer1:size":0},{"id":67,"source":"a***d","target":"/listing/2665/","weight":1,"color":"#37474f","hidden":false,"read_cam0:size":null,"renderer1:size":0},{"id":68,"source":"s***r","target":"/listing/2665/","weight":1,"color":"#37474f","hidden":false,"read_cam0:size":null,"renderer1:size":0},{"id":69,"source":"a***e","target":"/listing/2666/","weight":1,"color":"#37474f","hidden":false,"read_cam0:size":null,"renderer1:size":0},{"id":70,"source":"V***s","target":"/listing/2666/","weight":1,"color":"#37474f","hidden":false,"read_cam0:size":null,"renderer1:size":0},{"id":71,"source":"b***i","target":"/listing/2668/","weight":1,"color":"#37474f","hidden":false,"read_cam0:size":null,"renderer1:size":0},{"id":72,"source":"s***e","target":"/listing/2668/","weight":1,"color":"#37474f","hidden":false,"read_cam0:size":null,"renderer1:size":0},{"id":73,"source":"n***e","target":"/listing/2668/","weight":1,"color":"#37474f","hidden":false,"read_cam0:size":null,"renderer1:size":0},{"id":74,"source":"s***r","target":"/listing/2667/","weight":1,"color":"#37474f","hidden":false,"read_cam0:size":null,"renderer1:size":0},{"id":75,"source":"a***r","target":"/listing/2667/","weight":1,"color":"#37474f","hidden":false,"read_cam0:size":null,"renderer1:size":0},{"id":76,"source":"a***r","target":"/listing/2670/","weight":2,"color":"#37474f","hidden":false,"read_cam0:size":null,"renderer1:size":0},{"id":77,"source":"L***r","target":"/listing/3421/","weight":1,"color":"#37474f","hidden":false,"read_cam0:size":null,"renderer1:size":0},{"id":78,"source":"R***N","target":"/listing/3421/","weight":1,"color":"#37474f","hidden":false,"read_cam0:size":null,"renderer1:size":0},{"id":79,"source":"l***6","target":"/listing/3421/","weight":1,"color":"#37474f","hidden":false,"read_cam0:size":null,"renderer1:size":0},{"id":80,"source":"N***2","target":"/listing/3424/","weight":1,"color":"#37474f","hidden":false,"read_cam0:size":null,"renderer1:size":0},{"id":81,"source":"J***1","target":"/listing/3430/","weight":1,"color":"#37474f","hidden":false,"read_cam0:size":null,"renderer1:size":0},{"id":82,"source":"F***d","target":"/listing/8371/","weight":1,"color":"#37474f","hidden":false,"read_cam0:size":null,"renderer1:size":0},{"id":83,"source":"O***l","target":"/listing/9350/","weight":1,"color":"#37474f","hidden":false,"read_cam0:size":null,"renderer1:size":0},{"id":84,"source":"C***5","target":"/listing/9351/","weight":1,"color":"#37474f","hidden":false,"read_cam0:size":null,"renderer1:size":0},{"id":85,"source":"O***l","target":"/listing/9351/","weight":1,"color":"#37474f","hidden":false,"read_cam0:size":null,"renderer1:size":0},{"id":86,"source":"S***1","target":"/listing/9351/","weight":1,"color":"#37474f","hidden":false,"read_cam0:size":null,"renderer1:size":0},{"id":87,"source":"m***t","target":"/listing/9351/","weight":1,"color":"#37474f","hidden":false,"read_cam0:size":null,"renderer1:size":0},{"id":88,"source":"m***f","target":"/listing/9753/","weight":1,"color":"#37474f","hidden":false,"read_cam0:size":null,"renderer1:size":0}]}